[{"arguments":["clang","-Wno-documentation-unknown-command","-Wno-unknown-warning-option","-Wno-unknown-pragmas","-nostdinc","-nostdinc++","-g","-Wall","-Wextra","-Wextra","-fexceptions","-mthreads","-fsyntax-only","-m64","--target=x86_64-w64-mingw32","-std=gnu++17","-DUNICODE","-D_UNICODE","-DWIN32","-DMINGW_HAS_SECURE_API","-DGIFIMAGE_NO_LIB","-DQT_OPENGLWIDGETS_LIB","-DQT_OPENGL_LIB","-DQT_PRINTSUPPORT_LIB","-DQT_WIDGETS_LIB","-DQT_GUI_LIB","-DQT_CORE_LIB","-DQT_NEEDS_QMAIN","-DQ_CREATOR_RUN","-DQT_ANNOTATE_FUNCTION(x)=__attribute__((annotate(#x)))","-IC:\\Qt\\Tools\\QtCreator\\share\\qtcreator\\cplusplus\\wrappedMingwHeaders","-IC:\\Qt\\Tools\\QtCreator\\share\\qtcreator\\cplusplus\\wrappedQtHeaders","-IC:\\Qt\\Tools\\QtCreator\\share\\qtcreator\\cplusplus\\wrappedQtHeaders\\QtCore","-IC:\\Users\\Dima\\source\\repos\\CPP4_3DViewer_v2.0-2\\src\\3DView","-IC:\\Users\\Dima\\source\\repos\\CPP4_3DViewer_v2.0-2\\src\\3DView\\QtGifImage-master\\src\\gifimage","-IC:\\Users\\Dima\\source\\repos\\CPP4_3DViewer_v2.0-2\\src\\3DView\\QtGifImage-master\\src\\3rdParty\\giflib","-IC:\\Qt\\6.6.3\\mingw_64\\include","-IC:\\Qt\\6.6.3\\mingw_64\\include\\QtOpenGLWidgets","-IC:\\Qt\\6.6.3\\mingw_64\\include\\QtOpenGL","-IC:\\Qt\\6.6.3\\mingw_64\\include\\QtPrintSupport","-IC:\\Qt\\6.6.3\\mingw_64\\include\\QtWidgets","-IC:\\Qt\\6.6.3\\mingw_64\\include\\QtGui","-IC:\\Qt\\6.6.3\\mingw_64\\include\\QtCore","-IC:\\Users\\Dima\\source\\repos\\CPP4_3DViewer_v2.0-2\\src\\3DView\\build\\Desktop_Qt_6_6_3_MinGW_64_bit-Debug\\debug","-IC:\\Users\\Dima\\source\\repos\\CPP4_3DViewer_v2.0-2\\src\\3DView\\build\\Desktop_Qt_6_6_3_MinGW_64_bit-Debug","-IC:\\Qt\\6.6.3\\mingw_64\\mkspecs\\win32-g++","-isystem","C:\\Qt\\Tools\\mingw1120_64\\lib\\gcc\\x86_64-w64-mingw32\\11.2.0\\include\\c++","-isystem","C:\\Qt\\Tools\\mingw1120_64\\lib\\gcc\\x86_64-w64-mingw32\\11.2.0\\include\\c++\\x86_64-w64-mingw32","-isystem","C:\\Qt\\Tools\\mingw1120_64\\lib\\gcc\\x86_64-w64-mingw32\\11.2.0\\include\\c++\\backward","-isystem","C:\\Qt\\Tools\\QtCreator\\bin\\clang\\lib\\clang\\17\\include","-isystem","C:\\Qt\\Tools\\mingw1120_64\\x86_64-w64-mingw32\\include","-fmessage-length=0","-fdiagnostics-show-note-include-stack","-fretain-comments-from-system-headers","-fmacro-backtrace-limit=0","-ferror-limit=1000","-x","c++","C:\\Users\\Dima\\source\\repos\\CPP4_3DViewer_v2.0-2\\src\\3DView\\QtGifImage-master\\src\\gifimage\\qgifimage.cpp"],"directory":"C:/Users/Dima/source/repos/CPP4_3DViewer_v2.0-2/src/3DView/build/Desktop_Qt_6_6_3_MinGW_64_bit-Debug/.qtc_clangd","file":"C:/Users/Dima/source/repos/CPP4_3DViewer_v2.0-2/src/3DView/QtGifImage-master/src/gifimage/qgifimage.cpp"},{"arguments":["clang","-Wno-documentation-unknown-command","-Wno-unknown-warning-option","-Wno-unknown-pragmas","-nostdinc","-nostdinc++","-g","-Wall","-Wextra","-Wextra","-fexceptions","-mthreads","-fsyntax-only","-m64","--target=x86_64-w64-mingw32","-std=gnu++17","-DUNICODE","-D_UNICODE","-DWIN32","-DMINGW_HAS_SECURE_API","-DGIFIMAGE_NO_LIB","-DQT_OPENGLWIDGETS_LIB","-DQT_OPENGL_LIB","-DQT_PRINTSUPPORT_LIB","-DQT_WIDGETS_LIB","-DQT_GUI_LIB","-DQT_CORE_LIB","-DQT_NEEDS_QMAIN","-DQ_CREATOR_RUN","-DQT_ANNOTATE_FUNCTION(x)=__attribute__((annotate(#x)))","-IC:\\Qt\\Tools\\QtCreator\\share\\qtcreator\\cplusplus\\wrappedMingwHeaders","-IC:\\Qt\\Tools\\QtCreator\\share\\qtcreator\\cplusplus\\wrappedQtHeaders","-IC:\\Qt\\Tools\\QtCreator\\share\\qtcreator\\cplusplus\\wrappedQtHeaders\\QtCore","-IC:\\Users\\Dima\\source\\repos\\CPP4_3DViewer_v2.0-2\\src\\3DView","-IC:\\Users\\Dima\\source\\repos\\CPP4_3DViewer_v2.0-2\\src\\3DView\\QtGifImage-master\\src\\gifimage","-IC:\\Users\\Dima\\source\\repos\\CPP4_3DViewer_v2.0-2\\src\\3DView\\QtGifImage-master\\src\\3rdParty\\giflib","-IC:\\Qt\\6.6.3\\mingw_64\\include","-IC:\\Qt\\6.6.3\\mingw_64\\include\\QtOpenGLWidgets","-IC:\\Qt\\6.6.3\\mingw_64\\include\\QtOpenGL","-IC:\\Qt\\6.6.3\\mingw_64\\include\\QtPrintSupport","-IC:\\Qt\\6.6.3\\mingw_64\\include\\QtWidgets","-IC:\\Qt\\6.6.3\\mingw_64\\include\\QtGui","-IC:\\Qt\\6.6.3\\mingw_64\\include\\QtCore","-IC:\\Users\\Dima\\source\\repos\\CPP4_3DViewer_v2.0-2\\src\\3DView\\build\\Desktop_Qt_6_6_3_MinGW_64_bit-Debug\\debug","-IC:\\Users\\Dima\\source\\repos\\CPP4_3DViewer_v2.0-2\\src\\3DView\\build\\Desktop_Qt_6_6_3_MinGW_64_bit-Debug","-IC:\\Qt\\6.6.3\\mingw_64\\mkspecs\\win32-g++","-isystem","C:\\Qt\\Tools\\mingw1120_64\\lib\\gcc\\x86_64-w64-mingw32\\11.2.0\\include\\c++","-isystem","C:\\Qt\\Tools\\mingw1120_64\\lib\\gcc\\x86_64-w64-mingw32\\11.2.0\\include\\c++\\x86_64-w64-mingw32","-isystem","C:\\Qt\\Tools\\mingw1120_64\\lib\\gcc\\x86_64-w64-mingw32\\11.2.0\\include\\c++\\backward","-isystem","C:\\Qt\\Tools\\QtCreator\\bin\\clang\\lib\\clang\\17\\include","-isystem","C:\\Qt\\Tools\\mingw1120_64\\x86_64-w64-mingw32\\include","-fmessage-length=0","-fdiagnostics-show-note-include-stack","-fretain-comments-from-system-headers","-fmacro-backtrace-limit=0","-ferror-limit=1000","-x","c++","C:\\Users\\Dima\\source\\repos\\CPP4_3DViewer_v2.0-2\\src\\3DView\\model\\affine.cpp"],"directory":"C:/Users/Dima/source/repos/CPP4_3DViewer_v2.0-2/src/3DView/build/Desktop_Qt_6_6_3_MinGW_64_bit-Debug/.qtc_clangd","file":"C:/Users/Dima/source/repos/CPP4_3DViewer_v2.0-2/src/3DView/model/affine.cpp"},{"arguments":["clang","-Wno-documentation-unknown-command","-Wno-unknown-warning-option","-Wno-unknown-pragmas","-nostdinc","-nostdinc++","-g","-Wall","-Wextra","-Wextra","-fexceptions","-mthreads","-fsyntax-only","-m64","--target=x86_64-w64-mingw32","-std=gnu++17","-DUNICODE","-D_UNICODE","-DWIN32","-DMINGW_HAS_SECURE_API","-DGIFIMAGE_NO_LIB","-DQT_OPENGLWIDGETS_LIB","-DQT_OPENGL_LIB","-DQT_PRINTSUPPORT_LIB","-DQT_WIDGETS_LIB","-DQT_GUI_LIB","-DQT_CORE_LIB","-DQT_NEEDS_QMAIN","-DQ_CREATOR_RUN","-DQT_ANNOTATE_FUNCTION(x)=__attribute__((annotate(#x)))","-IC:\\Qt\\Tools\\QtCreator\\share\\qtcreator\\cplusplus\\wrappedMingwHeaders","-IC:\\Qt\\Tools\\QtCreator\\share\\qtcreator\\cplusplus\\wrappedQtHeaders","-IC:\\Qt\\Tools\\QtCreator\\share\\qtcreator\\cplusplus\\wrappedQtHeaders\\QtCore","-IC:\\Users\\Dima\\source\\repos\\CPP4_3DViewer_v2.0-2\\src\\3DView","-IC:\\Users\\Dima\\source\\repos\\CPP4_3DViewer_v2.0-2\\src\\3DView\\QtGifImage-master\\src\\gifimage","-IC:\\Users\\Dima\\source\\repos\\CPP4_3DViewer_v2.0-2\\src\\3DView\\QtGifImage-master\\src\\3rdParty\\giflib","-IC:\\Qt\\6.6.3\\mingw_64\\include","-IC:\\Qt\\6.6.3\\mingw_64\\include\\QtOpenGLWidgets","-IC:\\Qt\\6.6.3\\mingw_64\\include\\QtOpenGL","-IC:\\Qt\\6.6.3\\mingw_64\\include\\QtPrintSupport","-IC:\\Qt\\6.6.3\\mingw_64\\include\\QtWidgets","-IC:\\Qt\\6.6.3\\mingw_64\\include\\QtGui","-IC:\\Qt\\6.6.3\\mingw_64\\include\\QtCore","-IC:\\Users\\Dima\\source\\repos\\CPP4_3DViewer_v2.0-2\\src\\3DView\\build\\Desktop_Qt_6_6_3_MinGW_64_bit-Debug\\debug","-IC:\\Users\\Dima\\source\\repos\\CPP4_3DViewer_v2.0-2\\src\\3DView\\build\\Desktop_Qt_6_6_3_MinGW_64_bit-Debug","-IC:\\Qt\\6.6.3\\mingw_64\\mkspecs\\win32-g++","-isystem","C:\\Qt\\Tools\\mingw1120_64\\lib\\gcc\\x86_64-w64-mingw32\\11.2.0\\include\\c++","-isystem","C:\\Qt\\Tools\\mingw1120_64\\lib\\gcc\\x86_64-w64-mingw32\\11.2.0\\include\\c++\\x86_64-w64-mingw32","-isystem","C:\\Qt\\Tools\\mingw1120_64\\lib\\gcc\\x86_64-w64-mingw32\\11.2.0\\include\\c++\\backward","-isystem","C:\\Qt\\Tools\\QtCreator\\bin\\clang\\lib\\clang\\17\\include","-isystem","C:\\Qt\\Tools\\mingw1120_64\\x86_64-w64-mingw32\\include","-fmessage-length=0","-fdiagnostics-show-note-include-stack","-fretain-comments-from-system-headers","-fmacro-backtrace-limit=0","-ferror-limit=1000","-x","c++","C:\\Users\\Dima\\source\\repos\\CPP4_3DViewer_v2.0-2\\src\\3DView\\model\\facade.cpp"],"directory":"C:/Users/Dima/source/repos/CPP4_3DViewer_v2.0-2/src/3DView/build/Desktop_Qt_6_6_3_MinGW_64_bit-Debug/.qtc_clangd","file":"C:/Users/Dima/source/repos/CPP4_3DViewer_v2.0-2/src/3DView/model/facade.cpp"},{"arguments":["clang","-Wno-documentation-unknown-command","-Wno-unknown-warning-option","-Wno-unknown-pragmas","-nostdinc","-nostdinc++","-g","-Wall","-Wextra","-Wextra","-fexceptions","-mthreads","-fsyntax-only","-m64","--target=x86_64-w64-mingw32","-std=gnu++17","-DUNICODE","-D_UNICODE","-DWIN32","-DMINGW_HAS_SECURE_API","-DGIFIMAGE_NO_LIB","-DQT_OPENGLWIDGETS_LIB","-DQT_OPENGL_LIB","-DQT_PRINTSUPPORT_LIB","-DQT_WIDGETS_LIB","-DQT_GUI_LIB","-DQT_CORE_LIB","-DQT_NEEDS_QMAIN","-DQ_CREATOR_RUN","-DQT_ANNOTATE_FUNCTION(x)=__attribute__((annotate(#x)))","-IC:\\Qt\\Tools\\QtCreator\\share\\qtcreator\\cplusplus\\wrappedMingwHeaders","-IC:\\Qt\\Tools\\QtCreator\\share\\qtcreator\\cplusplus\\wrappedQtHeaders","-IC:\\Qt\\Tools\\QtCreator\\share\\qtcreator\\cplusplus\\wrappedQtHeaders\\QtCore","-IC:\\Users\\Dima\\source\\repos\\CPP4_3DViewer_v2.0-2\\src\\3DView","-IC:\\Users\\Dima\\source\\repos\\CPP4_3DViewer_v2.0-2\\src\\3DView\\QtGifImage-master\\src\\gifimage","-IC:\\Users\\Dima\\source\\repos\\CPP4_3DViewer_v2.0-2\\src\\3DView\\QtGifImage-master\\src\\3rdParty\\giflib","-IC:\\Qt\\6.6.3\\mingw_64\\include","-IC:\\Qt\\6.6.3\\mingw_64\\include\\QtOpenGLWidgets","-IC:\\Qt\\6.6.3\\mingw_64\\include\\QtOpenGL","-IC:\\Qt\\6.6.3\\mingw_64\\include\\QtPrintSupport","-IC:\\Qt\\6.6.3\\mingw_64\\include\\QtWidgets","-IC:\\Qt\\6.6.3\\mingw_64\\include\\QtGui","-IC:\\Qt\\6.6.3\\mingw_64\\include\\QtCore","-IC:\\Users\\Dima\\source\\repos\\CPP4_3DViewer_v2.0-2\\src\\3DView\\build\\Desktop_Qt_6_6_3_MinGW_64_bit-Debug\\debug","-IC:\\Users\\Dima\\source\\repos\\CPP4_3DViewer_v2.0-2\\src\\3DView\\build\\Desktop_Qt_6_6_3_MinGW_64_bit-Debug","-IC:\\Qt\\6.6.3\\mingw_64\\mkspecs\\win32-g++","-isystem","C:\\Qt\\Tools\\mingw1120_64\\lib\\gcc\\x86_64-w64-mingw32\\11.2.0\\include\\c++","-isystem","C:\\Qt\\Tools\\mingw1120_64\\lib\\gcc\\x86_64-w64-mingw32\\11.2.0\\include\\c++\\x86_64-w64-mingw32","-isystem","C:\\Qt\\Tools\\mingw1120_64\\lib\\gcc\\x86_64-w64-mingw32\\11.2.0\\include\\c++\\backward","-isystem","C:\\Qt\\Tools\\QtCreator\\bin\\clang\\lib\\clang\\17\\include","-isystem","C:\\Qt\\Tools\\mingw1120_64\\x86_64-w64-mingw32\\include","-fmessage-length=0","-fdiagnostics-show-note-include-stack","-fretain-comments-from-system-headers","-fmacro-backtrace-limit=0","-ferror-limit=1000","-x","c++","C:\\Users\\Dima\\source\\repos\\CPP4_3DViewer_v2.0-2\\src\\3DView\\model\\parser.cpp"],"directory":"C:/Users/Dima/source/repos/CPP4_3DViewer_v2.0-2/src/3DView/build/Desktop_Qt_6_6_3_MinGW_64_bit-Debug/.qtc_clangd","file":"C:/Users/Dima/source/repos/CPP4_3DViewer_v2.0-2/src/3DView/model/parser.cpp"},{"arguments":["clang","-Wno-documentation-unknown-command","-Wno-unknown-warning-option","-Wno-unknown-pragmas","-nostdinc","-nostdinc++","-g","-Wall","-Wextra","-Wextra","-fexceptions","-mthreads","-fsyntax-only","-m64","--target=x86_64-w64-mingw32","-std=gnu++17","-DUNICODE","-D_UNICODE","-DWIN32","-DMINGW_HAS_SECURE_API","-DGIFIMAGE_NO_LIB","-DQT_OPENGLWIDGETS_LIB","-DQT_OPENGL_LIB","-DQT_PRINTSUPPORT_LIB","-DQT_WIDGETS_LIB","-DQT_GUI_LIB","-DQT_CORE_LIB","-DQT_NEEDS_QMAIN","-DQ_CREATOR_RUN","-DQT_ANNOTATE_FUNCTION(x)=__attribute__((annotate(#x)))","-IC:\\Qt\\Tools\\QtCreator\\share\\qtcreator\\cplusplus\\wrappedMingwHeaders","-IC:\\Qt\\Tools\\QtCreator\\share\\qtcreator\\cplusplus\\wrappedQtHeaders","-IC:\\Qt\\Tools\\QtCreator\\share\\qtcreator\\cplusplus\\wrappedQtHeaders\\QtCore","-IC:\\Users\\Dima\\source\\repos\\CPP4_3DViewer_v2.0-2\\src\\3DView","-IC:\\Users\\Dima\\source\\repos\\CPP4_3DViewer_v2.0-2\\src\\3DView\\QtGifImage-master\\src\\gifimage","-IC:\\Users\\Dima\\source\\repos\\CPP4_3DViewer_v2.0-2\\src\\3DView\\QtGifImage-master\\src\\3rdParty\\giflib","-IC:\\Qt\\6.6.3\\mingw_64\\include","-IC:\\Qt\\6.6.3\\mingw_64\\include\\QtOpenGLWidgets","-IC:\\Qt\\6.6.3\\mingw_64\\include\\QtOpenGL","-IC:\\Qt\\6.6.3\\mingw_64\\include\\QtPrintSupport","-IC:\\Qt\\6.6.3\\mingw_64\\include\\QtWidgets","-IC:\\Qt\\6.6.3\\mingw_64\\include\\QtGui","-IC:\\Qt\\6.6.3\\mingw_64\\include\\QtCore","-IC:\\Users\\Dima\\source\\repos\\CPP4_3DViewer_v2.0-2\\src\\3DView\\build\\Desktop_Qt_6_6_3_MinGW_64_bit-Debug\\debug","-IC:\\Users\\Dima\\source\\repos\\CPP4_3DViewer_v2.0-2\\src\\3DView\\build\\Desktop_Qt_6_6_3_MinGW_64_bit-Debug","-IC:\\Qt\\6.6.3\\mingw_64\\mkspecs\\win32-g++","-isystem","C:\\Qt\\Tools\\mingw1120_64\\lib\\gcc\\x86_64-w64-mingw32\\11.2.0\\include\\c++","-isystem","C:\\Qt\\Tools\\mingw1120_64\\lib\\gcc\\x86_64-w64-mingw32\\11.2.0\\include\\c++\\x86_64-w64-mingw32","-isystem","C:\\Qt\\Tools\\mingw1120_64\\lib\\gcc\\x86_64-w64-mingw32\\11.2.0\\include\\c++\\backward","-isystem","C:\\Qt\\Tools\\QtCreator\\bin\\clang\\lib\\clang\\17\\include","-isystem","C:\\Qt\\Tools\\mingw1120_64\\x86_64-w64-mingw32\\include","-fmessage-length=0","-fdiagnostics-show-note-include-stack","-fretain-comments-from-system-headers","-fmacro-backtrace-limit=0","-ferror-limit=1000","-x","c++","C:\\Users\\Dima\\source\\repos\\CPP4_3DViewer_v2.0-2\\src\\3DView\\view\\glview.cpp"],"directory":"C:/Users/Dima/source/repos/CPP4_3DViewer_v2.0-2/src/3DView/build/Desktop_Qt_6_6_3_MinGW_64_bit-Debug/.qtc_clangd","file":"C:/Users/Dima/source/repos/CPP4_3DViewer_v2.0-2/src/3DView/view/glview.cpp"},{"arguments":["clang","-Wno-documentation-unknown-command","-Wno-unknown-warning-option","-Wno-unknown-pragmas","-nostdinc","-nostdinc++","-g","-Wall","-Wextra","-Wextra","-fexceptions","-mthreads","-fsyntax-only","-m64","--target=x86_64-w64-mingw32","-std=gnu++17","-DUNICODE","-D_UNICODE","-DWIN32","-DMINGW_HAS_SECURE_API","-DGIFIMAGE_NO_LIB","-DQT_OPENGLWIDGETS_LIB","-DQT_OPENGL_LIB","-DQT_PRINTSUPPORT_LIB","-DQT_WIDGETS_LIB","-DQT_GUI_LIB","-DQT_CORE_LIB","-DQT_NEEDS_QMAIN","-DQ_CREATOR_RUN","-DQT_ANNOTATE_FUNCTION(x)=__attribute__((annotate(#x)))","-IC:\\Qt\\Tools\\QtCreator\\share\\qtcreator\\cplusplus\\wrappedMingwHeaders","-IC:\\Qt\\Tools\\QtCreator\\share\\qtcreator\\cplusplus\\wrappedQtHeaders","-IC:\\Qt\\Tools\\QtCreator\\share\\qtcreator\\cplusplus\\wrappedQtHeaders\\QtCore","-IC:\\Users\\Dima\\source\\repos\\CPP4_3DViewer_v2.0-2\\src\\3DView","-IC:\\Users\\Dima\\source\\repos\\CPP4_3DViewer_v2.0-2\\src\\3DView\\QtGifImage-master\\src\\gifimage","-IC:\\Users\\Dima\\source\\repos\\CPP4_3DViewer_v2.0-2\\src\\3DView\\QtGifImage-master\\src\\3rdParty\\giflib","-IC:\\Qt\\6.6.3\\mingw_64\\include","-IC:\\Qt\\6.6.3\\mingw_64\\include\\QtOpenGLWidgets","-IC:\\Qt\\6.6.3\\mingw_64\\include\\QtOpenGL","-IC:\\Qt\\6.6.3\\mingw_64\\include\\QtPrintSupport","-IC:\\Qt\\6.6.3\\mingw_64\\include\\QtWidgets","-IC:\\Qt\\6.6.3\\mingw_64\\include\\QtGui","-IC:\\Qt\\6.6.3\\mingw_64\\include\\QtCore","-IC:\\Users\\Dima\\source\\repos\\CPP4_3DViewer_v2.0-2\\src\\3DView\\build\\Desktop_Qt_6_6_3_MinGW_64_bit-Debug\\debug","-IC:\\Users\\Dima\\source\\repos\\CPP4_3DViewer_v2.0-2\\src\\3DView\\build\\Desktop_Qt_6_6_3_MinGW_64_bit-Debug","-IC:\\Qt\\6.6.3\\mingw_64\\mkspecs\\win32-g++","-isystem","C:\\Qt\\Tools\\mingw1120_64\\lib\\gcc\\x86_64-w64-mingw32\\11.2.0\\include\\c++","-isystem","C:\\Qt\\Tools\\mingw1120_64\\lib\\gcc\\x86_64-w64-mingw32\\11.2.0\\include\\c++\\x86_64-w64-mingw32","-isystem","C:\\Qt\\Tools\\mingw1120_64\\lib\\gcc\\x86_64-w64-mingw32\\11.2.0\\include\\c++\\backward","-isystem","C:\\Qt\\Tools\\QtCreator\\bin\\clang\\lib\\clang\\17\\include","-isystem","C:\\Qt\\Tools\\mingw1120_64\\x86_64-w64-mingw32\\include","-fmessage-length=0","-fdiagnostics-show-note-include-stack","-fretain-comments-from-system-headers","-fmacro-backtrace-limit=0","-ferror-limit=1000","-x","c++","C:\\Users\\Dima\\source\\repos\\CPP4_3DViewer_v2.0-2\\src\\3DView\\main.cpp"],"directory":"C:/Users/Dima/source/repos/CPP4_3DViewer_v2.0-2/src/3DView/build/Desktop_Qt_6_6_3_MinGW_64_bit-Debug/.qtc_clangd","file":"C:/Users/Dima/source/repos/CPP4_3DViewer_v2.0-2/src/3DView/main.cpp"},{"arguments":["clang","-Wno-documentation-unknown-command","-Wno-unknown-warning-option","-Wno-unknown-pragmas","-nostdinc","-nostdinc++","-g","-Wall","-Wextra","-Wextra","-fexceptions","-mthreads","-fsyntax-only","-m64","--target=x86_64-w64-mingw32","-std=gnu++17","-DUNICODE","-D_UNICODE","-DWIN32","-DMINGW_HAS_SECURE_API","-DGIFIMAGE_NO_LIB","-DQT_OPENGLWIDGETS_LIB","-DQT_OPENGL_LIB","-DQT_PRINTSUPPORT_LIB","-DQT_WIDGETS_LIB","-DQT_GUI_LIB","-DQT_CORE_LIB","-DQT_NEEDS_QMAIN","-DQ_CREATOR_RUN","-DQT_ANNOTATE_FUNCTION(x)=__attribute__((annotate(#x)))","-IC:\\Qt\\Tools\\QtCreator\\share\\qtcreator\\cplusplus\\wrappedMingwHeaders","-IC:\\Qt\\Tools\\QtCreator\\share\\qtcreator\\cplusplus\\wrappedQtHeaders","-IC:\\Qt\\Tools\\QtCreator\\share\\qtcreator\\cplusplus\\wrappedQtHeaders\\QtCore","-IC:\\Users\\Dima\\source\\repos\\CPP4_3DViewer_v2.0-2\\src\\3DView","-IC:\\Users\\Dima\\source\\repos\\CPP4_3DViewer_v2.0-2\\src\\3DView\\QtGifImage-master\\src\\gifimage","-IC:\\Users\\Dima\\source\\repos\\CPP4_3DViewer_v2.0-2\\src\\3DView\\QtGifImage-master\\src\\3rdParty\\giflib","-IC:\\Qt\\6.6.3\\mingw_64\\include","-IC:\\Qt\\6.6.3\\mingw_64\\include\\QtOpenGLWidgets","-IC:\\Qt\\6.6.3\\mingw_64\\include\\QtOpenGL","-IC:\\Qt\\6.6.3\\mingw_64\\include\\QtPrintSupport","-IC:\\Qt\\6.6.3\\mingw_64\\include\\QtWidgets","-IC:\\Qt\\6.6.3\\mingw_64\\include\\QtGui","-IC:\\Qt\\6.6.3\\mingw_64\\include\\QtCore","-IC:\\Users\\Dima\\source\\repos\\CPP4_3DViewer_v2.0-2\\src\\3DView\\build\\Desktop_Qt_6_6_3_MinGW_64_bit-Debug\\debug","-IC:\\Users\\Dima\\source\\repos\\CPP4_3DViewer_v2.0-2\\src\\3DView\\build\\Desktop_Qt_6_6_3_MinGW_64_bit-Debug","-IC:\\Qt\\6.6.3\\mingw_64\\mkspecs\\win32-g++","-isystem","C:\\Qt\\Tools\\mingw1120_64\\lib\\gcc\\x86_64-w64-mingw32\\11.2.0\\include\\c++","-isystem","C:\\Qt\\Tools\\mingw1120_64\\lib\\gcc\\x86_64-w64-mingw32\\11.2.0\\include\\c++\\x86_64-w64-mingw32","-isystem","C:\\Qt\\Tools\\mingw1120_64\\lib\\gcc\\x86_64-w64-mingw32\\11.2.0\\include\\c++\\backward","-isystem","C:\\Qt\\Tools\\QtCreator\\bin\\clang\\lib\\clang\\17\\include","-isystem","C:\\Qt\\Tools\\mingw1120_64\\x86_64-w64-mingw32\\include","-fmessage-length=0","-fdiagnostics-show-note-include-stack","-fretain-comments-from-system-headers","-fmacro-backtrace-limit=0","-ferror-limit=1000","-x","c++","C:\\Users\\Dima\\source\\repos\\CPP4_3DViewer_v2.0-2\\src\\3DView\\mainwindow.cpp"],"directory":"C:/Users/Dima/source/repos/CPP4_3DViewer_v2.0-2/src/3DView/build/Desktop_Qt_6_6_3_MinGW_64_bit-Debug/.qtc_clangd","file":"C:/Users/Dima/source/repos/CPP4_3DViewer_v2.0-2/src/3DView/mainwindow.cpp"},{"arguments":["clang","-Wno-documentation-unknown-command","-Wno-unknown-warning-option","-Wno-unknown-pragmas","-nostdinc","-nostdinc++","-g","-Wall","-Wextra","-Wextra","-fexceptions","-mthreads","-fsyntax-only","-m64","--target=x86_64-w64-mingw32","-std=gnu++17","-DUNICODE","-D_UNICODE","-DWIN32","-DMINGW_HAS_SECURE_API","-DGIFIMAGE_NO_LIB","-DQT_OPENGLWIDGETS_LIB","-DQT_OPENGL_LIB","-DQT_PRINTSUPPORT_LIB","-DQT_WIDGETS_LIB","-DQT_GUI_LIB","-DQT_CORE_LIB","-DQT_NEEDS_QMAIN","-DQ_CREATOR_RUN","-DQT_ANNOTATE_FUNCTION(x)=__attribute__((annotate(#x)))","-IC:\\Qt\\Tools\\QtCreator\\share\\qtcreator\\cplusplus\\wrappedMingwHeaders","-IC:\\Qt\\Tools\\QtCreator\\share\\qtcreator\\cplusplus\\wrappedQtHeaders","-IC:\\Qt\\Tools\\QtCreator\\share\\qtcreator\\cplusplus\\wrappedQtHeaders\\QtCore","-IC:\\Users\\Dima\\source\\repos\\CPP4_3DViewer_v2.0-2\\src\\3DView","-IC:\\Users\\Dima\\source\\repos\\CPP4_3DViewer_v2.0-2\\src\\3DView\\QtGifImage-master\\src\\gifimage","-IC:\\Users\\Dima\\source\\repos\\CPP4_3DViewer_v2.0-2\\src\\3DView\\QtGifImage-master\\src\\3rdParty\\giflib","-IC:\\Qt\\6.6.3\\mingw_64\\include","-IC:\\Qt\\6.6.3\\mingw_64\\include\\QtOpenGLWidgets","-IC:\\Qt\\6.6.3\\mingw_64\\include\\QtOpenGL","-IC:\\Qt\\6.6.3\\mingw_64\\include\\QtPrintSupport","-IC:\\Qt\\6.6.3\\mingw_64\\include\\QtWidgets","-IC:\\Qt\\6.6.3\\mingw_64\\include\\QtGui","-IC:\\Qt\\6.6.3\\mingw_64\\include\\QtCore","-IC:\\Users\\Dima\\source\\repos\\CPP4_3DViewer_v2.0-2\\src\\3DView\\build\\Desktop_Qt_6_6_3_MinGW_64_bit-Debug\\debug","-IC:\\Users\\Dima\\source\\repos\\CPP4_3DViewer_v2.0-2\\src\\3DView\\build\\Desktop_Qt_6_6_3_MinGW_64_bit-Debug","-IC:\\Qt\\6.6.3\\mingw_64\\mkspecs\\win32-g++","-isystem","C:\\Qt\\Tools\\mingw1120_64\\lib\\gcc\\x86_64-w64-mingw32\\11.2.0\\include\\c++","-isystem","C:\\Qt\\Tools\\mingw1120_64\\lib\\gcc\\x86_64-w64-mingw32\\11.2.0\\include\\c++\\x86_64-w64-mingw32","-isystem","C:\\Qt\\Tools\\mingw1120_64\\lib\\gcc\\x86_64-w64-mingw32\\11.2.0\\include\\c++\\backward","-isystem","C:\\Qt\\Tools\\QtCreator\\bin\\clang\\lib\\clang\\17\\include","-isystem","C:\\Qt\\Tools\\mingw1120_64\\x86_64-w64-mingw32\\include","-fmessage-length=0","-fdiagnostics-show-note-include-stack","-fretain-comments-from-system-headers","-fmacro-backtrace-limit=0","-ferror-limit=1000","-x","c++","C:\\Users\\Dima\\source\\repos\\CPP4_3DViewer_v2.0-2\\src\\3DView\\view\\record_media.cpp"],"directory":"C:/Users/Dima/source/repos/CPP4_3DViewer_v2.0-2/src/3DView/build/Desktop_Qt_6_6_3_MinGW_64_bit-Debug/.qtc_clangd","file":"C:/Users/Dima/source/repos/CPP4_3DViewer_v2.0-2/src/3DView/view/record_media.cpp"},{"arguments":["clang","-Wno-documentation-unknown-command","-Wno-unknown-warning-option","-Wno-unknown-pragmas","-nostdinc","-nostdinc++","-g","-Wall","-Wextra","-Wextra","-fexceptions","-mthreads","-fsyntax-only","-m64","--target=x86_64-w64-mingw32","-std=gnu++17","-DUNICODE","-D_UNICODE","-DWIN32","-DMINGW_HAS_SECURE_API","-DGIFIMAGE_NO_LIB","-DQT_OPENGLWIDGETS_LIB","-DQT_OPENGL_LIB","-DQT_PRINTSUPPORT_LIB","-DQT_WIDGETS_LIB","-DQT_GUI_LIB","-DQT_CORE_LIB","-DQT_NEEDS_QMAIN","-DQ_CREATOR_RUN","-DQT_ANNOTATE_FUNCTION(x)=__attribute__((annotate(#x)))","-IC:\\Qt\\Tools\\QtCreator\\share\\qtcreator\\cplusplus\\wrappedMingwHeaders","-IC:\\Qt\\Tools\\QtCreator\\share\\qtcreator\\cplusplus\\wrappedQtHeaders","-IC:\\Qt\\Tools\\QtCreator\\share\\qtcreator\\cplusplus\\wrappedQtHeaders\\QtCore","-IC:\\Users\\Dima\\source\\repos\\CPP4_3DViewer_v2.0-2\\src\\3DView","-IC:\\Users\\Dima\\source\\repos\\CPP4_3DViewer_v2.0-2\\src\\3DView\\QtGifImage-master\\src\\gifimage","-IC:\\Users\\Dima\\source\\repos\\CPP4_3DViewer_v2.0-2\\src\\3DView\\QtGifImage-master\\src\\3rdParty\\giflib","-IC:\\Qt\\6.6.3\\mingw_64\\include","-IC:\\Qt\\6.6.3\\mingw_64\\include\\QtOpenGLWidgets","-IC:\\Qt\\6.6.3\\mingw_64\\include\\QtOpenGL","-IC:\\Qt\\6.6.3\\mingw_64\\include\\QtPrintSupport","-IC:\\Qt\\6.6.3\\mingw_64\\include\\QtWidgets","-IC:\\Qt\\6.6.3\\mingw_64\\include\\QtGui","-IC:\\Qt\\6.6.3\\mingw_64\\include\\QtCore","-IC:\\Users\\Dima\\source\\repos\\CPP4_3DViewer_v2.0-2\\src\\3DView\\build\\Desktop_Qt_6_6_3_MinGW_64_bit-Debug\\debug","-IC:\\Users\\Dima\\source\\repos\\CPP4_3DViewer_v2.0-2\\src\\3DView\\build\\Desktop_Qt_6_6_3_MinGW_64_bit-Debug","-IC:\\Qt\\6.6.3\\mingw_64\\mkspecs\\win32-g++","-isystem","C:\\Qt\\Tools\\mingw1120_64\\lib\\gcc\\x86_64-w64-mingw32\\11.2.0\\include\\c++","-isystem","C:\\Qt\\Tools\\mingw1120_64\\lib\\gcc\\x86_64-w64-mingw32\\11.2.0\\include\\c++\\x86_64-w64-mingw32","-isystem","C:\\Qt\\Tools\\mingw1120_64\\lib\\gcc\\x86_64-w64-mingw32\\11.2.0\\include\\c++\\backward","-isystem","C:\\Qt\\Tools\\QtCreator\\bin\\clang\\lib\\clang\\17\\include","-isystem","C:\\Qt\\Tools\\mingw1120_64\\x86_64-w64-mingw32\\include","-fmessage-length=0","-fdiagnostics-show-note-include-stack","-fretain-comments-from-system-headers","-fmacro-backtrace-limit=0","-ferror-limit=1000","-x","c++-header","C:\\Users\\Dima\\source\\repos\\CPP4_3DViewer_v2.0-2\\src\\3DView\\QtGifImage-master\\src\\gifimage\\qgifglobal.h"],"directory":"C:/Users/Dima/source/repos/CPP4_3DViewer_v2.0-2/src/3DView/build/Desktop_Qt_6_6_3_MinGW_64_bit-Debug/.qtc_clangd","file":"C:/Users/Dima/source/repos/CPP4_3DViewer_v2.0-2/src/3DView/QtGifImage-master/src/gifimage/qgifglobal.h"},{"arguments":["clang","-Wno-documentation-unknown-command","-Wno-unknown-warning-option","-Wno-unknown-pragmas","-nostdinc","-nostdinc++","-g","-Wall","-Wextra","-Wextra","-fexceptions","-mthreads","-fsyntax-only","-m64","--target=x86_64-w64-mingw32","-std=gnu++17","-DUNICODE","-D_UNICODE","-DWIN32","-DMINGW_HAS_SECURE_API","-DGIFIMAGE_NO_LIB","-DQT_OPENGLWIDGETS_LIB","-DQT_OPENGL_LIB","-DQT_PRINTSUPPORT_LIB","-DQT_WIDGETS_LIB","-DQT_GUI_LIB","-DQT_CORE_LIB","-DQT_NEEDS_QMAIN","-DQ_CREATOR_RUN","-DQT_ANNOTATE_FUNCTION(x)=__attribute__((annotate(#x)))","-IC:\\Qt\\Tools\\QtCreator\\share\\qtcreator\\cplusplus\\wrappedMingwHeaders","-IC:\\Qt\\Tools\\QtCreator\\share\\qtcreator\\cplusplus\\wrappedQtHeaders","-IC:\\Qt\\Tools\\QtCreator\\share\\qtcreator\\cplusplus\\wrappedQtHeaders\\QtCore","-IC:\\Users\\Dima\\source\\repos\\CPP4_3DViewer_v2.0-2\\src\\3DView","-IC:\\Users\\Dima\\source\\repos\\CPP4_3DViewer_v2.0-2\\src\\3DView\\QtGifImage-master\\src\\gifimage","-IC:\\Users\\Dima\\source\\repos\\CPP4_3DViewer_v2.0-2\\src\\3DView\\QtGifImage-master\\src\\3rdParty\\giflib","-IC:\\Qt\\6.6.3\\mingw_64\\include","-IC:\\Qt\\6.6.3\\mingw_64\\include\\QtOpenGLWidgets","-IC:\\Qt\\6.6.3\\mingw_64\\include\\QtOpenGL","-IC:\\Qt\\6.6.3\\mingw_64\\include\\QtPrintSupport","-IC:\\Qt\\6.6.3\\mingw_64\\include\\QtWidgets","-IC:\\Qt\\6.6.3\\mingw_64\\include\\QtGui","-IC:\\Qt\\6.6.3\\mingw_64\\include\\QtCore","-IC:\\Users\\Dima\\source\\repos\\CPP4_3DViewer_v2.0-2\\src\\3DView\\build\\Desktop_Qt_6_6_3_MinGW_64_bit-Debug\\debug","-IC:\\Users\\Dima\\source\\repos\\CPP4_3DViewer_v2.0-2\\src\\3DView\\build\\Desktop_Qt_6_6_3_MinGW_64_bit-Debug","-IC:\\Qt\\6.6.3\\mingw_64\\mkspecs\\win32-g++","-isystem","C:\\Qt\\Tools\\mingw1120_64\\lib\\gcc\\x86_64-w64-mingw32\\11.2.0\\include\\c++","-isystem","C:\\Qt\\Tools\\mingw1120_64\\lib\\gcc\\x86_64-w64-mingw32\\11.2.0\\include\\c++\\x86_64-w64-mingw32","-isystem","C:\\Qt\\Tools\\mingw1120_64\\lib\\gcc\\x86_64-w64-mingw32\\11.2.0\\include\\c++\\backward","-isystem","C:\\Qt\\Tools\\QtCreator\\bin\\clang\\lib\\clang\\17\\include","-isystem","C:\\Qt\\Tools\\mingw1120_64\\x86_64-w64-mingw32\\include","-fmessage-length=0","-fdiagnostics-show-note-include-stack","-fretain-comments-from-system-headers","-fmacro-backtrace-limit=0","-ferror-limit=1000","-x","c++-header","C:\\Users\\Dima\\source\\repos\\CPP4_3DViewer_v2.0-2\\src\\3DView\\QtGifImage-master\\src\\gifimage\\qgifimage.h"],"directory":"C:/Users/Dima/source/repos/CPP4_3DViewer_v2.0-2/src/3DView/build/Desktop_Qt_6_6_3_MinGW_64_bit-Debug/.qtc_clangd","file":"C:/Users/Dima/source/repos/CPP4_3DViewer_v2.0-2/src/3DView/QtGifImage-master/src/gifimage/qgifimage.h"},{"arguments":["clang","-Wno-documentation-unknown-command","-Wno-unknown-warning-option","-Wno-unknown-pragmas","-nostdinc","-nostdinc++","-g","-Wall","-Wextra","-Wextra","-fexceptions","-mthreads","-fsyntax-only","-m64","--target=x86_64-w64-mingw32","-std=gnu++17","-DUNICODE","-D_UNICODE","-DWIN32","-DMINGW_HAS_SECURE_API","-DGIFIMAGE_NO_LIB","-DQT_OPENGLWIDGETS_LIB","-DQT_OPENGL_LIB","-DQT_PRINTSUPPORT_LIB","-DQT_WIDGETS_LIB","-DQT_GUI_LIB","-DQT_CORE_LIB","-DQT_NEEDS_QMAIN","-DQ_CREATOR_RUN","-DQT_ANNOTATE_FUNCTION(x)=__attribute__((annotate(#x)))","-IC:\\Qt\\Tools\\QtCreator\\share\\qtcreator\\cplusplus\\wrappedMingwHeaders","-IC:\\Qt\\Tools\\QtCreator\\share\\qtcreator\\cplusplus\\wrappedQtHeaders","-IC:\\Qt\\Tools\\QtCreator\\share\\qtcreator\\cplusplus\\wrappedQtHeaders\\QtCore","-IC:\\Users\\Dima\\source\\repos\\CPP4_3DViewer_v2.0-2\\src\\3DView","-IC:\\Users\\Dima\\source\\repos\\CPP4_3DViewer_v2.0-2\\src\\3DView\\QtGifImage-master\\src\\gifimage","-IC:\\Users\\Dima\\source\\repos\\CPP4_3DViewer_v2.0-2\\src\\3DView\\QtGifImage-master\\src\\3rdParty\\giflib","-IC:\\Qt\\6.6.3\\mingw_64\\include","-IC:\\Qt\\6.6.3\\mingw_64\\include\\QtOpenGLWidgets","-IC:\\Qt\\6.6.3\\mingw_64\\include\\QtOpenGL","-IC:\\Qt\\6.6.3\\mingw_64\\include\\QtPrintSupport","-IC:\\Qt\\6.6.3\\mingw_64\\include\\QtWidgets","-IC:\\Qt\\6.6.3\\mingw_64\\include\\QtGui","-IC:\\Qt\\6.6.3\\mingw_64\\include\\QtCore","-IC:\\Users\\Dima\\source\\repos\\CPP4_3DViewer_v2.0-2\\src\\3DView\\build\\Desktop_Qt_6_6_3_MinGW_64_bit-Debug\\debug","-IC:\\Users\\Dima\\source\\repos\\CPP4_3DViewer_v2.0-2\\src\\3DView\\build\\Desktop_Qt_6_6_3_MinGW_64_bit-Debug","-IC:\\Qt\\6.6.3\\mingw_64\\mkspecs\\win32-g++","-isystem","C:\\Qt\\Tools\\mingw1120_64\\lib\\gcc\\x86_64-w64-mingw32\\11.2.0\\include\\c++","-isystem","C:\\Qt\\Tools\\mingw1120_64\\lib\\gcc\\x86_64-w64-mingw32\\11.2.0\\include\\c++\\x86_64-w64-mingw32","-isystem","C:\\Qt\\Tools\\mingw1120_64\\lib\\gcc\\x86_64-w64-mingw32\\11.2.0\\include\\c++\\backward","-isystem","C:\\Qt\\Tools\\QtCreator\\bin\\clang\\lib\\clang\\17\\include","-isystem","C:\\Qt\\Tools\\mingw1120_64\\x86_64-w64-mingw32\\include","-fmessage-length=0","-fdiagnostics-show-note-include-stack","-fretain-comments-from-system-headers","-fmacro-backtrace-limit=0","-ferror-limit=1000","-x","c++-header","C:\\Users\\Dima\\source\\repos\\CPP4_3DViewer_v2.0-2\\src\\3DView\\QtGifImage-master\\src\\gifimage\\qgifimage_p.h"],"directory":"C:/Users/Dima/source/repos/CPP4_3DViewer_v2.0-2/src/3DView/build/Desktop_Qt_6_6_3_MinGW_64_bit-Debug/.qtc_clangd","file":"C:/Users/Dima/source/repos/CPP4_3DViewer_v2.0-2/src/3DView/QtGifImage-master/src/gifimage/qgifimage_p.h"},{"arguments":["clang","-Wno-documentation-unknown-command","-Wno-unknown-warning-option","-Wno-unknown-pragmas","-nostdinc","-nostdinc++","-g","-Wall","-Wextra","-Wextra","-fexceptions","-mthreads","-fsyntax-only","-m64","--target=x86_64-w64-mingw32","-std=gnu++17","-DUNICODE","-D_UNICODE","-DWIN32","-DMINGW_HAS_SECURE_API","-DGIFIMAGE_NO_LIB","-DQT_OPENGLWIDGETS_LIB","-DQT_OPENGL_LIB","-DQT_PRINTSUPPORT_LIB","-DQT_WIDGETS_LIB","-DQT_GUI_LIB","-DQT_CORE_LIB","-DQT_NEEDS_QMAIN","-DQ_CREATOR_RUN","-DQT_ANNOTATE_FUNCTION(x)=__attribute__((annotate(#x)))","-IC:\\Qt\\Tools\\QtCreator\\share\\qtcreator\\cplusplus\\wrappedMingwHeaders","-IC:\\Qt\\Tools\\QtCreator\\share\\qtcreator\\cplusplus\\wrappedQtHeaders","-IC:\\Qt\\Tools\\QtCreator\\share\\qtcreator\\cplusplus\\wrappedQtHeaders\\QtCore","-IC:\\Users\\Dima\\source\\repos\\CPP4_3DViewer_v2.0-2\\src\\3DView","-IC:\\Users\\Dima\\source\\repos\\CPP4_3DViewer_v2.0-2\\src\\3DView\\QtGifImage-master\\src\\gifimage","-IC:\\Users\\Dima\\source\\repos\\CPP4_3DViewer_v2.0-2\\src\\3DView\\QtGifImage-master\\src\\3rdParty\\giflib","-IC:\\Qt\\6.6.3\\mingw_64\\include","-IC:\\Qt\\6.6.3\\mingw_64\\include\\QtOpenGLWidgets","-IC:\\Qt\\6.6.3\\mingw_64\\include\\QtOpenGL","-IC:\\Qt\\6.6.3\\mingw_64\\include\\QtPrintSupport","-IC:\\Qt\\6.6.3\\mingw_64\\include\\QtWidgets","-IC:\\Qt\\6.6.3\\mingw_64\\include\\QtGui","-IC:\\Qt\\6.6.3\\mingw_64\\include\\QtCore","-IC:\\Users\\Dima\\source\\repos\\CPP4_3DViewer_v2.0-2\\src\\3DView\\build\\Desktop_Qt_6_6_3_MinGW_64_bit-Debug\\debug","-IC:\\Users\\Dima\\source\\repos\\CPP4_3DViewer_v2.0-2\\src\\3DView\\build\\Desktop_Qt_6_6_3_MinGW_64_bit-Debug","-IC:\\Qt\\6.6.3\\mingw_64\\mkspecs\\win32-g++","-isystem","C:\\Qt\\Tools\\mingw1120_64\\lib\\gcc\\x86_64-w64-mingw32\\11.2.0\\include\\c++","-isystem","C:\\Qt\\Tools\\mingw1120_64\\lib\\gcc\\x86_64-w64-mingw32\\11.2.0\\include\\c++\\x86_64-w64-mingw32","-isystem","C:\\Qt\\Tools\\mingw1120_64\\lib\\gcc\\x86_64-w64-mingw32\\11.2.0\\include\\c++\\backward","-isystem","C:\\Qt\\Tools\\QtCreator\\bin\\clang\\lib\\clang\\17\\include","-isystem","C:\\Qt\\Tools\\mingw1120_64\\x86_64-w64-mingw32\\include","-fmessage-length=0","-fdiagnostics-show-note-include-stack","-fretain-comments-from-system-headers","-fmacro-backtrace-limit=0","-ferror-limit=1000","-x","c++-header","C:\\Users\\Dima\\source\\repos\\CPP4_3DViewer_v2.0-2\\src\\3DView\\model\\affine.h"],"directory":"C:/Users/Dima/source/repos/CPP4_3DViewer_v2.0-2/src/3DView/build/Desktop_Qt_6_6_3_MinGW_64_bit-Debug/.qtc_clangd","file":"C:/Users/Dima/source/repos/CPP4_3DViewer_v2.0-2/src/3DView/model/affine.h"},{"arguments":["clang","-Wno-documentation-unknown-command","-Wno-unknown-warning-option","-Wno-unknown-pragmas","-nostdinc","-nostdinc++","-g","-Wall","-Wextra","-Wextra","-fexceptions","-mthreads","-fsyntax-only","-m64","--target=x86_64-w64-mingw32","-std=gnu++17","-DUNICODE","-D_UNICODE","-DWIN32","-DMINGW_HAS_SECURE_API","-DGIFIMAGE_NO_LIB","-DQT_OPENGLWIDGETS_LIB","-DQT_OPENGL_LIB","-DQT_PRINTSUPPORT_LIB","-DQT_WIDGETS_LIB","-DQT_GUI_LIB","-DQT_CORE_LIB","-DQT_NEEDS_QMAIN","-DQ_CREATOR_RUN","-DQT_ANNOTATE_FUNCTION(x)=__attribute__((annotate(#x)))","-IC:\\Qt\\Tools\\QtCreator\\share\\qtcreator\\cplusplus\\wrappedMingwHeaders","-IC:\\Qt\\Tools\\QtCreator\\share\\qtcreator\\cplusplus\\wrappedQtHeaders","-IC:\\Qt\\Tools\\QtCreator\\share\\qtcreator\\cplusplus\\wrappedQtHeaders\\QtCore","-IC:\\Users\\Dima\\source\\repos\\CPP4_3DViewer_v2.0-2\\src\\3DView","-IC:\\Users\\Dima\\source\\repos\\CPP4_3DViewer_v2.0-2\\src\\3DView\\QtGifImage-master\\src\\gifimage","-IC:\\Users\\Dima\\source\\repos\\CPP4_3DViewer_v2.0-2\\src\\3DView\\QtGifImage-master\\src\\3rdParty\\giflib","-IC:\\Qt\\6.6.3\\mingw_64\\include","-IC:\\Qt\\6.6.3\\mingw_64\\include\\QtOpenGLWidgets","-IC:\\Qt\\6.6.3\\mingw_64\\include\\QtOpenGL","-IC:\\Qt\\6.6.3\\mingw_64\\include\\QtPrintSupport","-IC:\\Qt\\6.6.3\\mingw_64\\include\\QtWidgets","-IC:\\Qt\\6.6.3\\mingw_64\\include\\QtGui","-IC:\\Qt\\6.6.3\\mingw_64\\include\\QtCore","-IC:\\Users\\Dima\\source\\repos\\CPP4_3DViewer_v2.0-2\\src\\3DView\\build\\Desktop_Qt_6_6_3_MinGW_64_bit-Debug\\debug","-IC:\\Users\\Dima\\source\\repos\\CPP4_3DViewer_v2.0-2\\src\\3DView\\build\\Desktop_Qt_6_6_3_MinGW_64_bit-Debug","-IC:\\Qt\\6.6.3\\mingw_64\\mkspecs\\win32-g++","-isystem","C:\\Qt\\Tools\\mingw1120_64\\lib\\gcc\\x86_64-w64-mingw32\\11.2.0\\include\\c++","-isystem","C:\\Qt\\Tools\\mingw1120_64\\lib\\gcc\\x86_64-w64-mingw32\\11.2.0\\include\\c++\\x86_64-w64-mingw32","-isystem","C:\\Qt\\Tools\\mingw1120_64\\lib\\gcc\\x86_64-w64-mingw32\\11.2.0\\include\\c++\\backward","-isystem","C:\\Qt\\Tools\\QtCreator\\bin\\clang\\lib\\clang\\17\\include","-isystem","C:\\Qt\\Tools\\mingw1120_64\\x86_64-w64-mingw32\\include","-fmessage-length=0","-fdiagnostics-show-note-include-stack","-fretain-comments-from-system-headers","-fmacro-backtrace-limit=0","-ferror-limit=1000","-x","c++-header","C:\\Users\\Dima\\source\\repos\\CPP4_3DViewer_v2.0-2\\src\\3DView\\model\\facade.h"],"directory":"C:/Users/Dima/source/repos/CPP4_3DViewer_v2.0-2/src/3DView/build/Desktop_Qt_6_6_3_MinGW_64_bit-Debug/.qtc_clangd","file":"C:/Users/Dima/source/repos/CPP4_3DViewer_v2.0-2/src/3DView/model/facade.h"},{"arguments":["clang","-Wno-documentation-unknown-command","-Wno-unknown-warning-option","-Wno-unknown-pragmas","-nostdinc","-nostdinc++","-g","-Wall","-Wextra","-Wextra","-fexceptions","-mthreads","-fsyntax-only","-m64","--target=x86_64-w64-mingw32","-std=gnu++17","-DUNICODE","-D_UNICODE","-DWIN32","-DMINGW_HAS_SECURE_API","-DGIFIMAGE_NO_LIB","-DQT_OPENGLWIDGETS_LIB","-DQT_OPENGL_LIB","-DQT_PRINTSUPPORT_LIB","-DQT_WIDGETS_LIB","-DQT_GUI_LIB","-DQT_CORE_LIB","-DQT_NEEDS_QMAIN","-DQ_CREATOR_RUN","-DQT_ANNOTATE_FUNCTION(x)=__attribute__((annotate(#x)))","-IC:\\Qt\\Tools\\QtCreator\\share\\qtcreator\\cplusplus\\wrappedMingwHeaders","-IC:\\Qt\\Tools\\QtCreator\\share\\qtcreator\\cplusplus\\wrappedQtHeaders","-IC:\\Qt\\Tools\\QtCreator\\share\\qtcreator\\cplusplus\\wrappedQtHeaders\\QtCore","-IC:\\Users\\Dima\\source\\repos\\CPP4_3DViewer_v2.0-2\\src\\3DView","-IC:\\Users\\Dima\\source\\repos\\CPP4_3DViewer_v2.0-2\\src\\3DView\\QtGifImage-master\\src\\gifimage","-IC:\\Users\\Dima\\source\\repos\\CPP4_3DViewer_v2.0-2\\src\\3DView\\QtGifImage-master\\src\\3rdParty\\giflib","-IC:\\Qt\\6.6.3\\mingw_64\\include","-IC:\\Qt\\6.6.3\\mingw_64\\include\\QtOpenGLWidgets","-IC:\\Qt\\6.6.3\\mingw_64\\include\\QtOpenGL","-IC:\\Qt\\6.6.3\\mingw_64\\include\\QtPrintSupport","-IC:\\Qt\\6.6.3\\mingw_64\\include\\QtWidgets","-IC:\\Qt\\6.6.3\\mingw_64\\include\\QtGui","-IC:\\Qt\\6.6.3\\mingw_64\\include\\QtCore","-IC:\\Users\\Dima\\source\\repos\\CPP4_3DViewer_v2.0-2\\src\\3DView\\build\\Desktop_Qt_6_6_3_MinGW_64_bit-Debug\\debug","-IC:\\Users\\Dima\\source\\repos\\CPP4_3DViewer_v2.0-2\\src\\3DView\\build\\Desktop_Qt_6_6_3_MinGW_64_bit-Debug","-IC:\\Qt\\6.6.3\\mingw_64\\mkspecs\\win32-g++","-isystem","C:\\Qt\\Tools\\mingw1120_64\\lib\\gcc\\x86_64-w64-mingw32\\11.2.0\\include\\c++","-isystem","C:\\Qt\\Tools\\mingw1120_64\\lib\\gcc\\x86_64-w64-mingw32\\11.2.0\\include\\c++\\x86_64-w64-mingw32","-isystem","C:\\Qt\\Tools\\mingw1120_64\\lib\\gcc\\x86_64-w64-mingw32\\11.2.0\\include\\c++\\backward","-isystem","C:\\Qt\\Tools\\QtCreator\\bin\\clang\\lib\\clang\\17\\include","-isystem","C:\\Qt\\Tools\\mingw1120_64\\x86_64-w64-mingw32\\include","-fmessage-length=0","-fdiagnostics-show-note-include-stack","-fretain-comments-from-system-headers","-fmacro-backtrace-limit=0","-ferror-limit=1000","-x","c++-header","C:\\Users\\Dima\\source\\repos\\CPP4_3DViewer_v2.0-2\\src\\3DView\\model\\parser.h"],"directory":"C:/Users/Dima/source/repos/CPP4_3DViewer_v2.0-2/src/3DView/build/Desktop_Qt_6_6_3_MinGW_64_bit-Debug/.qtc_clangd","file":"C:/Users/Dima/source/repos/CPP4_3DViewer_v2.0-2/src/3DView/model/parser.h"},{"arguments":["clang","-Wno-documentation-unknown-command","-Wno-unknown-warning-option","-Wno-unknown-pragmas","-nostdinc","-nostdinc++","-g","-Wall","-Wextra","-Wextra","-fexceptions","-mthreads","-fsyntax-only","-m64","--target=x86_64-w64-mingw32","-std=gnu++17","-DUNICODE","-D_UNICODE","-DWIN32","-DMINGW_HAS_SECURE_API","-DGIFIMAGE_NO_LIB","-DQT_OPENGLWIDGETS_LIB","-DQT_OPENGL_LIB","-DQT_PRINTSUPPORT_LIB","-DQT_WIDGETS_LIB","-DQT_GUI_LIB","-DQT_CORE_LIB","-DQT_NEEDS_QMAIN","-DQ_CREATOR_RUN","-DQT_ANNOTATE_FUNCTION(x)=__attribute__((annotate(#x)))","-IC:\\Qt\\Tools\\QtCreator\\share\\qtcreator\\cplusplus\\wrappedMingwHeaders","-IC:\\Qt\\Tools\\QtCreator\\share\\qtcreator\\cplusplus\\wrappedQtHeaders","-IC:\\Qt\\Tools\\QtCreator\\share\\qtcreator\\cplusplus\\wrappedQtHeaders\\QtCore","-IC:\\Users\\Dima\\source\\repos\\CPP4_3DViewer_v2.0-2\\src\\3DView","-IC:\\Users\\Dima\\source\\repos\\CPP4_3DViewer_v2.0-2\\src\\3DView\\QtGifImage-master\\src\\gifimage","-IC:\\Users\\Dima\\source\\repos\\CPP4_3DViewer_v2.0-2\\src\\3DView\\QtGifImage-master\\src\\3rdParty\\giflib","-IC:\\Qt\\6.6.3\\mingw_64\\include","-IC:\\Qt\\6.6.3\\mingw_64\\include\\QtOpenGLWidgets","-IC:\\Qt\\6.6.3\\mingw_64\\include\\QtOpenGL","-IC:\\Qt\\6.6.3\\mingw_64\\include\\QtPrintSupport","-IC:\\Qt\\6.6.3\\mingw_64\\include\\QtWidgets","-IC:\\Qt\\6.6.3\\mingw_64\\include\\QtGui","-IC:\\Qt\\6.6.3\\mingw_64\\include\\QtCore","-IC:\\Users\\Dima\\source\\repos\\CPP4_3DViewer_v2.0-2\\src\\3DView\\build\\Desktop_Qt_6_6_3_MinGW_64_bit-Debug\\debug","-IC:\\Users\\Dima\\source\\repos\\CPP4_3DViewer_v2.0-2\\src\\3DView\\build\\Desktop_Qt_6_6_3_MinGW_64_bit-Debug","-IC:\\Qt\\6.6.3\\mingw_64\\mkspecs\\win32-g++","-isystem","C:\\Qt\\Tools\\mingw1120_64\\lib\\gcc\\x86_64-w64-mingw32\\11.2.0\\include\\c++","-isystem","C:\\Qt\\Tools\\mingw1120_64\\lib\\gcc\\x86_64-w64-mingw32\\11.2.0\\include\\c++\\x86_64-w64-mingw32","-isystem","C:\\Qt\\Tools\\mingw1120_64\\lib\\gcc\\x86_64-w64-mingw32\\11.2.0\\include\\c++\\backward","-isystem","C:\\Qt\\Tools\\QtCreator\\bin\\clang\\lib\\clang\\17\\include","-isystem","C:\\Qt\\Tools\\mingw1120_64\\x86_64-w64-mingw32\\include","-fmessage-length=0","-fdiagnostics-show-note-include-stack","-fretain-comments-from-system-headers","-fmacro-backtrace-limit=0","-ferror-limit=1000","-x","c++-header","C:\\Users\\Dima\\source\\repos\\CPP4_3DViewer_v2.0-2\\src\\3DView\\view\\glview.h"],"directory":"C:/Users/Dima/source/repos/CPP4_3DViewer_v2.0-2/src/3DView/build/Desktop_Qt_6_6_3_MinGW_64_bit-Debug/.qtc_clangd","file":"C:/Users/Dima/source/repos/CPP4_3DViewer_v2.0-2/src/3DView/view/glview.h"},{"arguments":["clang","-Wno-documentation-unknown-command","-Wno-unknown-warning-option","-Wno-unknown-pragmas","-nostdinc","-nostdinc++","-g","-Wall","-Wextra","-Wextra","-fexceptions","-mthreads","-fsyntax-only","-m64","--target=x86_64-w64-mingw32","-std=gnu++17","-DUNICODE","-D_UNICODE","-DWIN32","-DMINGW_HAS_SECURE_API","-DGIFIMAGE_NO_LIB","-DQT_OPENGLWIDGETS_LIB","-DQT_OPENGL_LIB","-DQT_PRINTSUPPORT_LIB","-DQT_WIDGETS_LIB","-DQT_GUI_LIB","-DQT_CORE_LIB","-DQT_NEEDS_QMAIN","-DQ_CREATOR_RUN","-DQT_ANNOTATE_FUNCTION(x)=__attribute__((annotate(#x)))","-IC:\\Qt\\Tools\\QtCreator\\share\\qtcreator\\cplusplus\\wrappedMingwHeaders","-IC:\\Qt\\Tools\\QtCreator\\share\\qtcreator\\cplusplus\\wrappedQtHeaders","-IC:\\Qt\\Tools\\QtCreator\\share\\qtcreator\\cplusplus\\wrappedQtHeaders\\QtCore","-IC:\\Users\\Dima\\source\\repos\\CPP4_3DViewer_v2.0-2\\src\\3DView","-IC:\\Users\\Dima\\source\\repos\\CPP4_3DViewer_v2.0-2\\src\\3DView\\QtGifImage-master\\src\\gifimage","-IC:\\Users\\Dima\\source\\repos\\CPP4_3DViewer_v2.0-2\\src\\3DView\\QtGifImage-master\\src\\3rdParty\\giflib","-IC:\\Qt\\6.6.3\\mingw_64\\include","-IC:\\Qt\\6.6.3\\mingw_64\\include\\QtOpenGLWidgets","-IC:\\Qt\\6.6.3\\mingw_64\\include\\QtOpenGL","-IC:\\Qt\\6.6.3\\mingw_64\\include\\QtPrintSupport","-IC:\\Qt\\6.6.3\\mingw_64\\include\\QtWidgets","-IC:\\Qt\\6.6.3\\mingw_64\\include\\QtGui","-IC:\\Qt\\6.6.3\\mingw_64\\include\\QtCore","-IC:\\Users\\Dima\\source\\repos\\CPP4_3DViewer_v2.0-2\\src\\3DView\\build\\Desktop_Qt_6_6_3_MinGW_64_bit-Debug\\debug","-IC:\\Users\\Dima\\source\\repos\\CPP4_3DViewer_v2.0-2\\src\\3DView\\build\\Desktop_Qt_6_6_3_MinGW_64_bit-Debug","-IC:\\Qt\\6.6.3\\mingw_64\\mkspecs\\win32-g++","-isystem","C:\\Qt\\Tools\\mingw1120_64\\lib\\gcc\\x86_64-w64-mingw32\\11.2.0\\include\\c++","-isystem","C:\\Qt\\Tools\\mingw1120_64\\lib\\gcc\\x86_64-w64-mingw32\\11.2.0\\include\\c++\\x86_64-w64-mingw32","-isystem","C:\\Qt\\Tools\\mingw1120_64\\lib\\gcc\\x86_64-w64-mingw32\\11.2.0\\include\\c++\\backward","-isystem","C:\\Qt\\Tools\\QtCreator\\bin\\clang\\lib\\clang\\17\\include","-isystem","C:\\Qt\\Tools\\mingw1120_64\\x86_64-w64-mingw32\\include","-fmessage-length=0","-fdiagnostics-show-note-include-stack","-fretain-comments-from-system-headers","-fmacro-backtrace-limit=0","-ferror-limit=1000","-x","c++-header","C:\\Users\\Dima\\source\\repos\\CPP4_3DViewer_v2.0-2\\src\\3DView\\mainwindow.h"],"directory":"C:/Users/Dima/source/repos/CPP4_3DViewer_v2.0-2/src/3DView/build/Desktop_Qt_6_6_3_MinGW_64_bit-Debug/.qtc_clangd","file":"C:/Users/Dima/source/repos/CPP4_3DViewer_v2.0-2/src/3DView/mainwindow.h"},{"arguments":["clang","-Wno-documentation-unknown-command","-Wno-unknown-warning-option","-Wno-unknown-pragmas","-nostdinc","-nostdinc++","-g","-Wall","-Wextra","-Wextra","-fexceptions","-mthreads","-fsyntax-only","-m64","--target=x86_64-w64-mingw32","-std=gnu++17","-DUNICODE","-D_UNICODE","-DWIN32","-DMINGW_HAS_SECURE_API","-DGIFIMAGE_NO_LIB","-DQT_OPENGLWIDGETS_LIB","-DQT_OPENGL_LIB","-DQT_PRINTSUPPORT_LIB","-DQT_WIDGETS_LIB","-DQT_GUI_LIB","-DQT_CORE_LIB","-DQT_NEEDS_QMAIN","-DQ_CREATOR_RUN","-DQT_ANNOTATE_FUNCTION(x)=__attribute__((annotate(#x)))","-IC:\\Qt\\Tools\\QtCreator\\share\\qtcreator\\cplusplus\\wrappedMingwHeaders","-IC:\\Qt\\Tools\\QtCreator\\share\\qtcreator\\cplusplus\\wrappedQtHeaders","-IC:\\Qt\\Tools\\QtCreator\\share\\qtcreator\\cplusplus\\wrappedQtHeaders\\QtCore","-IC:\\Users\\Dima\\source\\repos\\CPP4_3DViewer_v2.0-2\\src\\3DView","-IC:\\Users\\Dima\\source\\repos\\CPP4_3DViewer_v2.0-2\\src\\3DView\\QtGifImage-master\\src\\gifimage","-IC:\\Users\\Dima\\source\\repos\\CPP4_3DViewer_v2.0-2\\src\\3DView\\QtGifImage-master\\src\\3rdParty\\giflib","-IC:\\Qt\\6.6.3\\mingw_64\\include","-IC:\\Qt\\6.6.3\\mingw_64\\include\\QtOpenGLWidgets","-IC:\\Qt\\6.6.3\\mingw_64\\include\\QtOpenGL","-IC:\\Qt\\6.6.3\\mingw_64\\include\\QtPrintSupport","-IC:\\Qt\\6.6.3\\mingw_64\\include\\QtWidgets","-IC:\\Qt\\6.6.3\\mingw_64\\include\\QtGui","-IC:\\Qt\\6.6.3\\mingw_64\\include\\QtCore","-IC:\\Users\\Dima\\source\\repos\\CPP4_3DViewer_v2.0-2\\src\\3DView\\build\\Desktop_Qt_6_6_3_MinGW_64_bit-Debug\\debug","-IC:\\Users\\Dima\\source\\repos\\CPP4_3DViewer_v2.0-2\\src\\3DView\\build\\Desktop_Qt_6_6_3_MinGW_64_bit-Debug","-IC:\\Qt\\6.6.3\\mingw_64\\mkspecs\\win32-g++","-isystem","C:\\Qt\\Tools\\mingw1120_64\\lib\\gcc\\x86_64-w64-mingw32\\11.2.0\\include\\c++","-isystem","C:\\Qt\\Tools\\mingw1120_64\\lib\\gcc\\x86_64-w64-mingw32\\11.2.0\\include\\c++\\x86_64-w64-mingw32","-isystem","C:\\Qt\\Tools\\mingw1120_64\\lib\\gcc\\x86_64-w64-mingw32\\11.2.0\\include\\c++\\backward","-isystem","C:\\Qt\\Tools\\QtCreator\\bin\\clang\\lib\\clang\\17\\include","-isystem","C:\\Qt\\Tools\\mingw1120_64\\x86_64-w64-mingw32\\include","-fmessage-length=0","-fdiagnostics-show-note-include-stack","-fretain-comments-from-system-headers","-fmacro-backtrace-limit=0","-ferror-limit=1000","-x","c++-header","C:\\Users\\Dima\\source\\repos\\CPP4_3DViewer_v2.0-2\\src\\3DView\\view\\record_media.h"],"directory":"C:/Users/Dima/source/repos/CPP4_3DViewer_v2.0-2/src/3DView/build/Desktop_Qt_6_6_3_MinGW_64_bit-Debug/.qtc_clangd","file":"C:/Users/Dima/source/repos/CPP4_3DViewer_v2.0-2/src/3DView/view/record_media.h"},{"arguments":["clang","-Wno-documentation-unknown-command","-Wno-unknown-warning-option","-Wno-unknown-pragmas","-nostdinc","-nostdinc++","-g","-Wall","-Wextra","-Wextra","-fexceptions","-mthreads","-fsyntax-only","-m64","--target=x86_64-w64-mingw32","-std=gnu++17","-DUNICODE","-D_UNICODE","-DWIN32","-DMINGW_HAS_SECURE_API","-DGIFIMAGE_NO_LIB","-DQT_OPENGLWIDGETS_LIB","-DQT_OPENGL_LIB","-DQT_PRINTSUPPORT_LIB","-DQT_WIDGETS_LIB","-DQT_GUI_LIB","-DQT_CORE_LIB","-DQT_NEEDS_QMAIN","-DQ_CREATOR_RUN","-DQT_ANNOTATE_FUNCTION(x)=__attribute__((annotate(#x)))","-IC:\\Qt\\Tools\\QtCreator\\share\\qtcreator\\cplusplus\\wrappedMingwHeaders","-IC:\\Qt\\Tools\\QtCreator\\share\\qtcreator\\cplusplus\\wrappedQtHeaders","-IC:\\Qt\\Tools\\QtCreator\\share\\qtcreator\\cplusplus\\wrappedQtHeaders\\QtCore","-IC:\\Users\\Dima\\source\\repos\\CPP4_3DViewer_v2.0-2\\src\\3DView","-IC:\\Users\\Dima\\source\\repos\\CPP4_3DViewer_v2.0-2\\src\\3DView\\QtGifImage-master\\src\\gifimage","-IC:\\Users\\Dima\\source\\repos\\CPP4_3DViewer_v2.0-2\\src\\3DView\\QtGifImage-master\\src\\3rdParty\\giflib","-IC:\\Qt\\6.6.3\\mingw_64\\include","-IC:\\Qt\\6.6.3\\mingw_64\\include\\QtOpenGLWidgets","-IC:\\Qt\\6.6.3\\mingw_64\\include\\QtOpenGL","-IC:\\Qt\\6.6.3\\mingw_64\\include\\QtPrintSupport","-IC:\\Qt\\6.6.3\\mingw_64\\include\\QtWidgets","-IC:\\Qt\\6.6.3\\mingw_64\\include\\QtGui","-IC:\\Qt\\6.6.3\\mingw_64\\include\\QtCore","-IC:\\Users\\Dima\\source\\repos\\CPP4_3DViewer_v2.0-2\\src\\3DView\\build\\Desktop_Qt_6_6_3_MinGW_64_bit-Debug\\debug","-IC:\\Users\\Dima\\source\\repos\\CPP4_3DViewer_v2.0-2\\src\\3DView\\build\\Desktop_Qt_6_6_3_MinGW_64_bit-Debug","-IC:\\Qt\\6.6.3\\mingw_64\\mkspecs\\win32-g++","-isystem","C:\\Qt\\Tools\\mingw1120_64\\lib\\gcc\\x86_64-w64-mingw32\\11.2.0\\include\\c++","-isystem","C:\\Qt\\Tools\\mingw1120_64\\lib\\gcc\\x86_64-w64-mingw32\\11.2.0\\include\\c++\\x86_64-w64-mingw32","-isystem","C:\\Qt\\Tools\\mingw1120_64\\lib\\gcc\\x86_64-w64-mingw32\\11.2.0\\include\\c++\\backward","-isystem","C:\\Qt\\Tools\\QtCreator\\bin\\clang\\lib\\clang\\17\\include","-isystem","C:\\Qt\\Tools\\mingw1120_64\\x86_64-w64-mingw32\\include","-fmessage-length=0","-fdiagnostics-show-note-include-stack","-fretain-comments-from-system-headers","-fmacro-backtrace-limit=0","-ferror-limit=1000","-x","c++-header","C:\\Users\\Dima\\source\\repos\\CPP4_3DViewer_v2.0-2\\src\\3DView\\build\\Desktop_Qt_6_6_3_MinGW_64_bit-Debug\\ui_mainwindow.h"],"directory":"C:/Users/Dima/source/repos/CPP4_3DViewer_v2.0-2/src/3DView/build/Desktop_Qt_6_6_3_MinGW_64_bit-Debug/.qtc_clangd","file":"C:/Users/Dima/source/repos/CPP4_3DViewer_v2.0-2/src/3DView/build/Desktop_Qt_6_6_3_MinGW_64_bit-Debug/ui_mainwindow.h"},{"arguments":["clang","-Wno-documentation-unknown-command","-Wno-unknown-warning-option","-Wno-unknown-pragmas","-nostdinc","-nostdinc++","-g","-Wall","-Wextra","-Wextra","-fsyntax-only","-m64","--target=x86_64-w64-mingw32","-std=gnu17","-DUNICODE","-D_UNICODE","-DWIN32","-DMINGW_HAS_SECURE_API","-DGIFIMAGE_NO_LIB","-DQT_OPENGLWIDGETS_LIB","-DQT_OPENGL_LIB","-DQT_PRINTSUPPORT_LIB","-DQT_WIDGETS_LIB","-DQT_GUI_LIB","-DQT_CORE_LIB","-DQT_NEEDS_QMAIN","-DQ_CREATOR_RUN","-DQT_ANNOTATE_FUNCTION(x)=__attribute__((annotate(#x)))","-IC:\\Qt\\Tools\\QtCreator\\share\\qtcreator\\cplusplus\\wrappedMingwHeaders","-IC:\\Qt\\Tools\\QtCreator\\share\\qtcreator\\cplusplus\\wrappedQtHeaders","-IC:\\Qt\\Tools\\QtCreator\\share\\qtcreator\\cplusplus\\wrappedQtHeaders\\QtCore","-IC:\\Users\\Dima\\source\\repos\\CPP4_3DViewer_v2.0-2\\src\\3DView","-IC:\\Users\\Dima\\source\\repos\\CPP4_3DViewer_v2.0-2\\src\\3DView\\QtGifImage-master\\src\\gifimage","-IC:\\Users\\Dima\\source\\repos\\CPP4_3DViewer_v2.0-2\\src\\3DView\\QtGifImage-master\\src\\3rdParty\\giflib","-IC:\\Qt\\6.6.3\\mingw_64\\include","-IC:\\Qt\\6.6.3\\mingw_64\\include\\QtOpenGLWidgets","-IC:\\Qt\\6.6.3\\mingw_64\\include\\QtOpenGL","-IC:\\Qt\\6.6.3\\mingw_64\\include\\QtPrintSupport","-IC:\\Qt\\6.6.3\\mingw_64\\include\\QtWidgets","-IC:\\Qt\\6.6.3\\mingw_64\\include\\QtGui","-IC:\\Qt\\6.6.3\\mingw_64\\include\\QtCore","-IC:\\Users\\Dima\\source\\repos\\CPP4_3DViewer_v2.0-2\\src\\3DView\\build\\Desktop_Qt_6_6_3_MinGW_64_bit-Debug\\debug","-IC:\\Users\\Dima\\source\\repos\\CPP4_3DViewer_v2.0-2\\src\\3DView\\build\\Desktop_Qt_6_6_3_MinGW_64_bit-Debug","-IC:\\Qt\\6.6.3\\mingw_64\\mkspecs\\win32-g++","-isystem","C:\\Qt\\Tools\\QtCreator\\bin\\clang\\lib\\clang\\17\\include","-isystem","C:\\Qt\\Tools\\mingw1120_64\\x86_64-w64-mingw32\\include","-fmessage-length=0","-fdiagnostics-show-note-include-stack","-fretain-comments-from-system-headers","-fmacro-backtrace-limit=0","-ferror-limit=1000","-x","c","C:\\Users\\Dima\\source\\repos\\CPP4_3DViewer_v2.0-2\\src\\3DView\\QtGifImage-master\\src\\3rdParty\\giflib\\dgif_lib.c"],"directory":"C:/Users/Dima/source/repos/CPP4_3DViewer_v2.0-2/src/3DView/build/Desktop_Qt_6_6_3_MinGW_64_bit-Debug/.qtc_clangd","file":"C:/Users/Dima/source/repos/CPP4_3DViewer_v2.0-2/src/3DView/QtGifImage-master/src/3rdParty/giflib/dgif_lib.c"},{"arguments":["clang","-Wno-documentation-unknown-command","-Wno-unknown-warning-option","-Wno-unknown-pragmas","-nostdinc","-nostdinc++","-g","-Wall","-Wextra","-Wextra","-fsyntax-only","-m64","--target=x86_64-w64-mingw32","-std=gnu17","-DUNICODE","-D_UNICODE","-DWIN32","-DMINGW_HAS_SECURE_API","-DGIFIMAGE_NO_LIB","-DQT_OPENGLWIDGETS_LIB","-DQT_OPENGL_LIB","-DQT_PRINTSUPPORT_LIB","-DQT_WIDGETS_LIB","-DQT_GUI_LIB","-DQT_CORE_LIB","-DQT_NEEDS_QMAIN","-DQ_CREATOR_RUN","-DQT_ANNOTATE_FUNCTION(x)=__attribute__((annotate(#x)))","-IC:\\Qt\\Tools\\QtCreator\\share\\qtcreator\\cplusplus\\wrappedMingwHeaders","-IC:\\Qt\\Tools\\QtCreator\\share\\qtcreator\\cplusplus\\wrappedQtHeaders","-IC:\\Qt\\Tools\\QtCreator\\share\\qtcreator\\cplusplus\\wrappedQtHeaders\\QtCore","-IC:\\Users\\Dima\\source\\repos\\CPP4_3DViewer_v2.0-2\\src\\3DView","-IC:\\Users\\Dima\\source\\repos\\CPP4_3DViewer_v2.0-2\\src\\3DView\\QtGifImage-master\\src\\gifimage","-IC:\\Users\\Dima\\source\\repos\\CPP4_3DViewer_v2.0-2\\src\\3DView\\QtGifImage-master\\src\\3rdParty\\giflib","-IC:\\Qt\\6.6.3\\mingw_64\\include","-IC:\\Qt\\6.6.3\\mingw_64\\include\\QtOpenGLWidgets","-IC:\\Qt\\6.6.3\\mingw_64\\include\\QtOpenGL","-IC:\\Qt\\6.6.3\\mingw_64\\include\\QtPrintSupport","-IC:\\Qt\\6.6.3\\mingw_64\\include\\QtWidgets","-IC:\\Qt\\6.6.3\\mingw_64\\include\\QtGui","-IC:\\Qt\\6.6.3\\mingw_64\\include\\QtCore","-IC:\\Users\\Dima\\source\\repos\\CPP4_3DViewer_v2.0-2\\src\\3DView\\build\\Desktop_Qt_6_6_3_MinGW_64_bit-Debug\\debug","-IC:\\Users\\Dima\\source\\repos\\CPP4_3DViewer_v2.0-2\\src\\3DView\\build\\Desktop_Qt_6_6_3_MinGW_64_bit-Debug","-IC:\\Qt\\6.6.3\\mingw_64\\mkspecs\\win32-g++","-isystem","C:\\Qt\\Tools\\QtCreator\\bin\\clang\\lib\\clang\\17\\include","-isystem","C:\\Qt\\Tools\\mingw1120_64\\x86_64-w64-mingw32\\include","-fmessage-length=0","-fdiagnostics-show-note-include-stack","-fretain-comments-from-system-headers","-fmacro-backtrace-limit=0","-ferror-limit=1000","-x","c","C:\\Users\\Dima\\source\\repos\\CPP4_3DViewer_v2.0-2\\src\\3DView\\QtGifImage-master\\src\\3rdParty\\giflib\\egif_lib.c"],"directory":"C:/Users/Dima/source/repos/CPP4_3DViewer_v2.0-2/src/3DView/build/Desktop_Qt_6_6_3_MinGW_64_bit-Debug/.qtc_clangd","file":"C:/Users/Dima/source/repos/CPP4_3DViewer_v2.0-2/src/3DView/QtGifImage-master/src/3rdParty/giflib/egif_lib.c"},{"arguments":["clang","-Wno-documentation-unknown-command","-Wno-unknown-warning-option","-Wno-unknown-pragmas","-nostdinc","-nostdinc++","-g","-Wall","-Wextra","-Wextra","-fsyntax-only","-m64","--target=x86_64-w64-mingw32","-std=gnu17","-DUNICODE","-D_UNICODE","-DWIN32","-DMINGW_HAS_SECURE_API","-DGIFIMAGE_NO_LIB","-DQT_OPENGLWIDGETS_LIB","-DQT_OPENGL_LIB","-DQT_PRINTSUPPORT_LIB","-DQT_WIDGETS_LIB","-DQT_GUI_LIB","-DQT_CORE_LIB","-DQT_NEEDS_QMAIN","-DQ_CREATOR_RUN","-DQT_ANNOTATE_FUNCTION(x)=__attribute__((annotate(#x)))","-IC:\\Qt\\Tools\\QtCreator\\share\\qtcreator\\cplusplus\\wrappedMingwHeaders","-IC:\\Qt\\Tools\\QtCreator\\share\\qtcreator\\cplusplus\\wrappedQtHeaders","-IC:\\Qt\\Tools\\QtCreator\\share\\qtcreator\\cplusplus\\wrappedQtHeaders\\QtCore","-IC:\\Users\\Dima\\source\\repos\\CPP4_3DViewer_v2.0-2\\src\\3DView","-IC:\\Users\\Dima\\source\\repos\\CPP4_3DViewer_v2.0-2\\src\\3DView\\QtGifImage-master\\src\\gifimage","-IC:\\Users\\Dima\\source\\repos\\CPP4_3DViewer_v2.0-2\\src\\3DView\\QtGifImage-master\\src\\3rdParty\\giflib","-IC:\\Qt\\6.6.3\\mingw_64\\include","-IC:\\Qt\\6.6.3\\mingw_64\\include\\QtOpenGLWidgets","-IC:\\Qt\\6.6.3\\mingw_64\\include\\QtOpenGL","-IC:\\Qt\\6.6.3\\mingw_64\\include\\QtPrintSupport","-IC:\\Qt\\6.6.3\\mingw_64\\include\\QtWidgets","-IC:\\Qt\\6.6.3\\mingw_64\\include\\QtGui","-IC:\\Qt\\6.6.3\\mingw_64\\include\\QtCore","-IC:\\Users\\Dima\\source\\repos\\CPP4_3DViewer_v2.0-2\\src\\3DView\\build\\Desktop_Qt_6_6_3_MinGW_64_bit-Debug\\debug","-IC:\\Users\\Dima\\source\\repos\\CPP4_3DViewer_v2.0-2\\src\\3DView\\build\\Desktop_Qt_6_6_3_MinGW_64_bit-Debug","-IC:\\Qt\\6.6.3\\mingw_64\\mkspecs\\win32-g++","-isystem","C:\\Qt\\Tools\\QtCreator\\bin\\clang\\lib\\clang\\17\\include","-isystem","C:\\Qt\\Tools\\mingw1120_64\\x86_64-w64-mingw32\\include","-fmessage-length=0","-fdiagnostics-show-note-include-stack","-fretain-comments-from-system-headers","-fmacro-backtrace-limit=0","-ferror-limit=1000","-x","c","C:\\Users\\Dima\\source\\repos\\CPP4_3DViewer_v2.0-2\\src\\3DView\\QtGifImage-master\\src\\3rdParty\\giflib\\gif_err.c"],"directory":"C:/Users/Dima/source/repos/CPP4_3DViewer_v2.0-2/src/3DView/build/Desktop_Qt_6_6_3_MinGW_64_bit-Debug/.qtc_clangd","file":"C:/Users/Dima/source/repos/CPP4_3DViewer_v2.0-2/src/3DView/QtGifImage-master/src/3rdParty/giflib/gif_err.c"},{"arguments":["clang","-Wno-documentation-unknown-command","-Wno-unknown-warning-option","-Wno-unknown-pragmas","-nostdinc","-nostdinc++","-g","-Wall","-Wextra","-Wextra","-fsyntax-only","-m64","--target=x86_64-w64-mingw32","-std=gnu17","-DUNICODE","-D_UNICODE","-DWIN32","-DMINGW_HAS_SECURE_API","-DGIFIMAGE_NO_LIB","-DQT_OPENGLWIDGETS_LIB","-DQT_OPENGL_LIB","-DQT_PRINTSUPPORT_LIB","-DQT_WIDGETS_LIB","-DQT_GUI_LIB","-DQT_CORE_LIB","-DQT_NEEDS_QMAIN","-DQ_CREATOR_RUN","-DQT_ANNOTATE_FUNCTION(x)=__attribute__((annotate(#x)))","-IC:\\Qt\\Tools\\QtCreator\\share\\qtcreator\\cplusplus\\wrappedMingwHeaders","-IC:\\Qt\\Tools\\QtCreator\\share\\qtcreator\\cplusplus\\wrappedQtHeaders","-IC:\\Qt\\Tools\\QtCreator\\share\\qtcreator\\cplusplus\\wrappedQtHeaders\\QtCore","-IC:\\Users\\Dima\\source\\repos\\CPP4_3DViewer_v2.0-2\\src\\3DView","-IC:\\Users\\Dima\\source\\repos\\CPP4_3DViewer_v2.0-2\\src\\3DView\\QtGifImage-master\\src\\gifimage","-IC:\\Users\\Dima\\source\\repos\\CPP4_3DViewer_v2.0-2\\src\\3DView\\QtGifImage-master\\src\\3rdParty\\giflib","-IC:\\Qt\\6.6.3\\mingw_64\\include","-IC:\\Qt\\6.6.3\\mingw_64\\include\\QtOpenGLWidgets","-IC:\\Qt\\6.6.3\\mingw_64\\include\\QtOpenGL","-IC:\\Qt\\6.6.3\\mingw_64\\include\\QtPrintSupport","-IC:\\Qt\\6.6.3\\mingw_64\\include\\QtWidgets","-IC:\\Qt\\6.6.3\\mingw_64\\include\\QtGui","-IC:\\Qt\\6.6.3\\mingw_64\\include\\QtCore","-IC:\\Users\\Dima\\source\\repos\\CPP4_3DViewer_v2.0-2\\src\\3DView\\build\\Desktop_Qt_6_6_3_MinGW_64_bit-Debug\\debug","-IC:\\Users\\Dima\\source\\repos\\CPP4_3DViewer_v2.0-2\\src\\3DView\\build\\Desktop_Qt_6_6_3_MinGW_64_bit-Debug","-IC:\\Qt\\6.6.3\\mingw_64\\mkspecs\\win32-g++","-isystem","C:\\Qt\\Tools\\QtCreator\\bin\\clang\\lib\\clang\\17\\include","-isystem","C:\\Qt\\Tools\\mingw1120_64\\x86_64-w64-mingw32\\include","-fmessage-length=0","-fdiagnostics-show-note-include-stack","-fretain-comments-from-system-headers","-fmacro-backtrace-limit=0","-ferror-limit=1000","-x","c","C:\\Users\\Dima\\source\\repos\\CPP4_3DViewer_v2.0-2\\src\\3DView\\QtGifImage-master\\src\\3rdParty\\giflib\\gif_hash.c"],"directory":"C:/Users/Dima/source/repos/CPP4_3DViewer_v2.0-2/src/3DView/build/Desktop_Qt_6_6_3_MinGW_64_bit-Debug/.qtc_clangd","file":"C:/Users/Dima/source/repos/CPP4_3DViewer_v2.0-2/src/3DView/QtGifImage-master/src/3rdParty/giflib/gif_hash.c"},{"arguments":["clang","-Wno-documentation-unknown-command","-Wno-unknown-warning-option","-Wno-unknown-pragmas","-nostdinc","-nostdinc++","-g","-Wall","-Wextra","-Wextra","-fsyntax-only","-m64","--target=x86_64-w64-mingw32","-std=gnu17","-DUNICODE","-D_UNICODE","-DWIN32","-DMINGW_HAS_SECURE_API","-DGIFIMAGE_NO_LIB","-DQT_OPENGLWIDGETS_LIB","-DQT_OPENGL_LIB","-DQT_PRINTSUPPORT_LIB","-DQT_WIDGETS_LIB","-DQT_GUI_LIB","-DQT_CORE_LIB","-DQT_NEEDS_QMAIN","-DQ_CREATOR_RUN","-DQT_ANNOTATE_FUNCTION(x)=__attribute__((annotate(#x)))","-IC:\\Qt\\Tools\\QtCreator\\share\\qtcreator\\cplusplus\\wrappedMingwHeaders","-IC:\\Qt\\Tools\\QtCreator\\share\\qtcreator\\cplusplus\\wrappedQtHeaders","-IC:\\Qt\\Tools\\QtCreator\\share\\qtcreator\\cplusplus\\wrappedQtHeaders\\QtCore","-IC:\\Users\\Dima\\source\\repos\\CPP4_3DViewer_v2.0-2\\src\\3DView","-IC:\\Users\\Dima\\source\\repos\\CPP4_3DViewer_v2.0-2\\src\\3DView\\QtGifImage-master\\src\\gifimage","-IC:\\Users\\Dima\\source\\repos\\CPP4_3DViewer_v2.0-2\\src\\3DView\\QtGifImage-master\\src\\3rdParty\\giflib","-IC:\\Qt\\6.6.3\\mingw_64\\include","-IC:\\Qt\\6.6.3\\mingw_64\\include\\QtOpenGLWidgets","-IC:\\Qt\\6.6.3\\mingw_64\\include\\QtOpenGL","-IC:\\Qt\\6.6.3\\mingw_64\\include\\QtPrintSupport","-IC:\\Qt\\6.6.3\\mingw_64\\include\\QtWidgets","-IC:\\Qt\\6.6.3\\mingw_64\\include\\QtGui","-IC:\\Qt\\6.6.3\\mingw_64\\include\\QtCore","-IC:\\Users\\Dima\\source\\repos\\CPP4_3DViewer_v2.0-2\\src\\3DView\\build\\Desktop_Qt_6_6_3_MinGW_64_bit-Debug\\debug","-IC:\\Users\\Dima\\source\\repos\\CPP4_3DViewer_v2.0-2\\src\\3DView\\build\\Desktop_Qt_6_6_3_MinGW_64_bit-Debug","-IC:\\Qt\\6.6.3\\mingw_64\\mkspecs\\win32-g++","-isystem","C:\\Qt\\Tools\\QtCreator\\bin\\clang\\lib\\clang\\17\\include","-isystem","C:\\Qt\\Tools\\mingw1120_64\\x86_64-w64-mingw32\\include","-fmessage-length=0","-fdiagnostics-show-note-include-stack","-fretain-comments-from-system-headers","-fmacro-backtrace-limit=0","-ferror-limit=1000","-x","c","C:\\Users\\Dima\\source\\repos\\CPP4_3DViewer_v2.0-2\\src\\3DView\\QtGifImage-master\\src\\3rdParty\\giflib\\gifalloc.c"],"directory":"C:/Users/Dima/source/repos/CPP4_3DViewer_v2.0-2/src/3DView/build/Desktop_Qt_6_6_3_MinGW_64_bit-Debug/.qtc_clangd","file":"C:/Users/Dima/source/repos/CPP4_3DViewer_v2.0-2/src/3DView/QtGifImage-master/src/3rdParty/giflib/gifalloc.c"},{"arguments":["clang","-Wno-documentation-unknown-command","-Wno-unknown-warning-option","-Wno-unknown-pragmas","-nostdinc","-nostdinc++","-g","-Wall","-Wextra","-Wextra","-fsyntax-only","-m64","--target=x86_64-w64-mingw32","-std=gnu17","-DUNICODE","-D_UNICODE","-DWIN32","-DMINGW_HAS_SECURE_API","-DGIFIMAGE_NO_LIB","-DQT_OPENGLWIDGETS_LIB","-DQT_OPENGL_LIB","-DQT_PRINTSUPPORT_LIB","-DQT_WIDGETS_LIB","-DQT_GUI_LIB","-DQT_CORE_LIB","-DQT_NEEDS_QMAIN","-DQ_CREATOR_RUN","-DQT_ANNOTATE_FUNCTION(x)=__attribute__((annotate(#x)))","-IC:\\Qt\\Tools\\QtCreator\\share\\qtcreator\\cplusplus\\wrappedMingwHeaders","-IC:\\Qt\\Tools\\QtCreator\\share\\qtcreator\\cplusplus\\wrappedQtHeaders","-IC:\\Qt\\Tools\\QtCreator\\share\\qtcreator\\cplusplus\\wrappedQtHeaders\\QtCore","-IC:\\Users\\Dima\\source\\repos\\CPP4_3DViewer_v2.0-2\\src\\3DView","-IC:\\Users\\Dima\\source\\repos\\CPP4_3DViewer_v2.0-2\\src\\3DView\\QtGifImage-master\\src\\gifimage","-IC:\\Users\\Dima\\source\\repos\\CPP4_3DViewer_v2.0-2\\src\\3DView\\QtGifImage-master\\src\\3rdParty\\giflib","-IC:\\Qt\\6.6.3\\mingw_64\\include","-IC:\\Qt\\6.6.3\\mingw_64\\include\\QtOpenGLWidgets","-IC:\\Qt\\6.6.3\\mingw_64\\include\\QtOpenGL","-IC:\\Qt\\6.6.3\\mingw_64\\include\\QtPrintSupport","-IC:\\Qt\\6.6.3\\mingw_64\\include\\QtWidgets","-IC:\\Qt\\6.6.3\\mingw_64\\include\\QtGui","-IC:\\Qt\\6.6.3\\mingw_64\\include\\QtCore","-IC:\\Users\\Dima\\source\\repos\\CPP4_3DViewer_v2.0-2\\src\\3DView\\build\\Desktop_Qt_6_6_3_MinGW_64_bit-Debug\\debug","-IC:\\Users\\Dima\\source\\repos\\CPP4_3DViewer_v2.0-2\\src\\3DView\\build\\Desktop_Qt_6_6_3_MinGW_64_bit-Debug","-IC:\\Qt\\6.6.3\\mingw_64\\mkspecs\\win32-g++","-isystem","C:\\Qt\\Tools\\QtCreator\\bin\\clang\\lib\\clang\\17\\include","-isystem","C:\\Qt\\Tools\\mingw1120_64\\x86_64-w64-mingw32\\include","-fmessage-length=0","-fdiagnostics-show-note-include-stack","-fretain-comments-from-system-headers","-fmacro-backtrace-limit=0","-ferror-limit=1000","-x","c","C:\\Users\\Dima\\source\\repos\\CPP4_3DViewer_v2.0-2\\src\\3DView\\QtGifImage-master\\src\\3rdParty\\giflib\\quantize.c"],"directory":"C:/Users/Dima/source/repos/CPP4_3DViewer_v2.0-2/src/3DView/build/Desktop_Qt_6_6_3_MinGW_64_bit-Debug/.qtc_clangd","file":"C:/Users/Dima/source/repos/CPP4_3DViewer_v2.0-2/src/3DView/QtGifImage-master/src/3rdParty/giflib/quantize.c"},{"arguments":["clang","-Wno-documentation-unknown-command","-Wno-unknown-warning-option","-Wno-unknown-pragmas","-nostdinc","-nostdinc++","-g","-Wall","-Wextra","-Wextra","-fsyntax-only","-m64","--target=x86_64-w64-mingw32","-std=gnu17","-DUNICODE","-D_UNICODE","-DWIN32","-DMINGW_HAS_SECURE_API","-DGIFIMAGE_NO_LIB","-DQT_OPENGLWIDGETS_LIB","-DQT_OPENGL_LIB","-DQT_PRINTSUPPORT_LIB","-DQT_WIDGETS_LIB","-DQT_GUI_LIB","-DQT_CORE_LIB","-DQT_NEEDS_QMAIN","-DQ_CREATOR_RUN","-DQT_ANNOTATE_FUNCTION(x)=__attribute__((annotate(#x)))","-IC:\\Qt\\Tools\\QtCreator\\share\\qtcreator\\cplusplus\\wrappedMingwHeaders","-IC:\\Qt\\Tools\\QtCreator\\share\\qtcreator\\cplusplus\\wrappedQtHeaders","-IC:\\Qt\\Tools\\QtCreator\\share\\qtcreator\\cplusplus\\wrappedQtHeaders\\QtCore","-IC:\\Users\\Dima\\source\\repos\\CPP4_3DViewer_v2.0-2\\src\\3DView","-IC:\\Users\\Dima\\source\\repos\\CPP4_3DViewer_v2.0-2\\src\\3DView\\QtGifImage-master\\src\\gifimage","-IC:\\Users\\Dima\\source\\repos\\CPP4_3DViewer_v2.0-2\\src\\3DView\\QtGifImage-master\\src\\3rdParty\\giflib","-IC:\\Qt\\6.6.3\\mingw_64\\include","-IC:\\Qt\\6.6.3\\mingw_64\\include\\QtOpenGLWidgets","-IC:\\Qt\\6.6.3\\mingw_64\\include\\QtOpenGL","-IC:\\Qt\\6.6.3\\mingw_64\\include\\QtPrintSupport","-IC:\\Qt\\6.6.3\\mingw_64\\include\\QtWidgets","-IC:\\Qt\\6.6.3\\mingw_64\\include\\QtGui","-IC:\\Qt\\6.6.3\\mingw_64\\include\\QtCore","-IC:\\Users\\Dima\\source\\repos\\CPP4_3DViewer_v2.0-2\\src\\3DView\\build\\Desktop_Qt_6_6_3_MinGW_64_bit-Debug\\debug","-IC:\\Users\\Dima\\source\\repos\\CPP4_3DViewer_v2.0-2\\src\\3DView\\build\\Desktop_Qt_6_6_3_MinGW_64_bit-Debug","-IC:\\Qt\\6.6.3\\mingw_64\\mkspecs\\win32-g++","-isystem","C:\\Qt\\Tools\\QtCreator\\bin\\clang\\lib\\clang\\17\\include","-isystem","C:\\Qt\\Tools\\mingw1120_64\\x86_64-w64-mingw32\\include","-fmessage-length=0","-fdiagnostics-show-note-include-stack","-fretain-comments-from-system-headers","-fmacro-backtrace-limit=0","-ferror-limit=1000","-x","c-header","C:\\Users\\Dima\\source\\repos\\CPP4_3DViewer_v2.0-2\\src\\3DView\\QtGifImage-master\\src\\gifimage\\qgifglobal.h"],"directory":"C:/Users/Dima/source/repos/CPP4_3DViewer_v2.0-2/src/3DView/build/Desktop_Qt_6_6_3_MinGW_64_bit-Debug/.qtc_clangd","file":"C:/Users/Dima/source/repos/CPP4_3DViewer_v2.0-2/src/3DView/QtGifImage-master/src/gifimage/qgifglobal.h"},{"arguments":["clang","-Wno-documentation-unknown-command","-Wno-unknown-warning-option","-Wno-unknown-pragmas","-nostdinc","-nostdinc++","-g","-Wall","-Wextra","-Wextra","-fsyntax-only","-m64","--target=x86_64-w64-mingw32","-std=gnu17","-DUNICODE","-D_UNICODE","-DWIN32","-DMINGW_HAS_SECURE_API","-DGIFIMAGE_NO_LIB","-DQT_OPENGLWIDGETS_LIB","-DQT_OPENGL_LIB","-DQT_PRINTSUPPORT_LIB","-DQT_WIDGETS_LIB","-DQT_GUI_LIB","-DQT_CORE_LIB","-DQT_NEEDS_QMAIN","-DQ_CREATOR_RUN","-DQT_ANNOTATE_FUNCTION(x)=__attribute__((annotate(#x)))","-IC:\\Qt\\Tools\\QtCreator\\share\\qtcreator\\cplusplus\\wrappedMingwHeaders","-IC:\\Qt\\Tools\\QtCreator\\share\\qtcreator\\cplusplus\\wrappedQtHeaders","-IC:\\Qt\\Tools\\QtCreator\\share\\qtcreator\\cplusplus\\wrappedQtHeaders\\QtCore","-IC:\\Users\\Dima\\source\\repos\\CPP4_3DViewer_v2.0-2\\src\\3DView","-IC:\\Users\\Dima\\source\\repos\\CPP4_3DViewer_v2.0-2\\src\\3DView\\QtGifImage-master\\src\\gifimage","-IC:\\Users\\Dima\\source\\repos\\CPP4_3DViewer_v2.0-2\\src\\3DView\\QtGifImage-master\\src\\3rdParty\\giflib","-IC:\\Qt\\6.6.3\\mingw_64\\include","-IC:\\Qt\\6.6.3\\mingw_64\\include\\QtOpenGLWidgets","-IC:\\Qt\\6.6.3\\mingw_64\\include\\QtOpenGL","-IC:\\Qt\\6.6.3\\mingw_64\\include\\QtPrintSupport","-IC:\\Qt\\6.6.3\\mingw_64\\include\\QtWidgets","-IC:\\Qt\\6.6.3\\mingw_64\\include\\QtGui","-IC:\\Qt\\6.6.3\\mingw_64\\include\\QtCore","-IC:\\Users\\Dima\\source\\repos\\CPP4_3DViewer_v2.0-2\\src\\3DView\\build\\Desktop_Qt_6_6_3_MinGW_64_bit-Debug\\debug","-IC:\\Users\\Dima\\source\\repos\\CPP4_3DViewer_v2.0-2\\src\\3DView\\build\\Desktop_Qt_6_6_3_MinGW_64_bit-Debug","-IC:\\Qt\\6.6.3\\mingw_64\\mkspecs\\win32-g++","-isystem","C:\\Qt\\Tools\\QtCreator\\bin\\clang\\lib\\clang\\17\\include","-isystem","C:\\Qt\\Tools\\mingw1120_64\\x86_64-w64-mingw32\\include","-fmessage-length=0","-fdiagnostics-show-note-include-stack","-fretain-comments-from-system-headers","-fmacro-backtrace-limit=0","-ferror-limit=1000","-x","c-header","C:\\Users\\Dima\\source\\repos\\CPP4_3DViewer_v2.0-2\\src\\3DView\\QtGifImage-master\\src\\gifimage\\qgifimage.h"],"directory":"C:/Users/Dima/source/repos/CPP4_3DViewer_v2.0-2/src/3DView/build/Desktop_Qt_6_6_3_MinGW_64_bit-Debug/.qtc_clangd","file":"C:/Users/Dima/source/repos/CPP4_3DViewer_v2.0-2/src/3DView/QtGifImage-master/src/gifimage/qgifimage.h"},{"arguments":["clang","-Wno-documentation-unknown-command","-Wno-unknown-warning-option","-Wno-unknown-pragmas","-nostdinc","-nostdinc++","-g","-Wall","-Wextra","-Wextra","-fsyntax-only","-m64","--target=x86_64-w64-mingw32","-std=gnu17","-DUNICODE","-D_UNICODE","-DWIN32","-DMINGW_HAS_SECURE_API","-DGIFIMAGE_NO_LIB","-DQT_OPENGLWIDGETS_LIB","-DQT_OPENGL_LIB","-DQT_PRINTSUPPORT_LIB","-DQT_WIDGETS_LIB","-DQT_GUI_LIB","-DQT_CORE_LIB","-DQT_NEEDS_QMAIN","-DQ_CREATOR_RUN","-DQT_ANNOTATE_FUNCTION(x)=__attribute__((annotate(#x)))","-IC:\\Qt\\Tools\\QtCreator\\share\\qtcreator\\cplusplus\\wrappedMingwHeaders","-IC:\\Qt\\Tools\\QtCreator\\share\\qtcreator\\cplusplus\\wrappedQtHeaders","-IC:\\Qt\\Tools\\QtCreator\\share\\qtcreator\\cplusplus\\wrappedQtHeaders\\QtCore","-IC:\\Users\\Dima\\source\\repos\\CPP4_3DViewer_v2.0-2\\src\\3DView","-IC:\\Users\\Dima\\source\\repos\\CPP4_3DViewer_v2.0-2\\src\\3DView\\QtGifImage-master\\src\\gifimage","-IC:\\Users\\Dima\\source\\repos\\CPP4_3DViewer_v2.0-2\\src\\3DView\\QtGifImage-master\\src\\3rdParty\\giflib","-IC:\\Qt\\6.6.3\\mingw_64\\include","-IC:\\Qt\\6.6.3\\mingw_64\\include\\QtOpenGLWidgets","-IC:\\Qt\\6.6.3\\mingw_64\\include\\QtOpenGL","-IC:\\Qt\\6.6.3\\mingw_64\\include\\QtPrintSupport","-IC:\\Qt\\6.6.3\\mingw_64\\include\\QtWidgets","-IC:\\Qt\\6.6.3\\mingw_64\\include\\QtGui","-IC:\\Qt\\6.6.3\\mingw_64\\include\\QtCore","-IC:\\Users\\Dima\\source\\repos\\CPP4_3DViewer_v2.0-2\\src\\3DView\\build\\Desktop_Qt_6_6_3_MinGW_64_bit-Debug\\debug","-IC:\\Users\\Dima\\source\\repos\\CPP4_3DViewer_v2.0-2\\src\\3DView\\build\\Desktop_Qt_6_6_3_MinGW_64_bit-Debug","-IC:\\Qt\\6.6.3\\mingw_64\\mkspecs\\win32-g++","-isystem","C:\\Qt\\Tools\\QtCreator\\bin\\clang\\lib\\clang\\17\\include","-isystem","C:\\Qt\\Tools\\mingw1120_64\\x86_64-w64-mingw32\\include","-fmessage-length=0","-fdiagnostics-show-note-include-stack","-fretain-comments-from-system-headers","-fmacro-backtrace-limit=0","-ferror-limit=1000","-x","c-header","C:\\Users\\Dima\\source\\repos\\CPP4_3DViewer_v2.0-2\\src\\3DView\\QtGifImage-master\\src\\gifimage\\qgifimage_p.h"],"directory":"C:/Users/Dima/source/repos/CPP4_3DViewer_v2.0-2/src/3DView/build/Desktop_Qt_6_6_3_MinGW_64_bit-Debug/.qtc_clangd","file":"C:/Users/Dima/source/repos/CPP4_3DViewer_v2.0-2/src/3DView/QtGifImage-master/src/gifimage/qgifimage_p.h"},{"arguments":["clang","-Wno-documentation-unknown-command","-Wno-unknown-warning-option","-Wno-unknown-pragmas","-nostdinc","-nostdinc++","-g","-Wall","-Wextra","-Wextra","-fsyntax-only","-m64","--target=x86_64-w64-mingw32","-std=gnu17","-DUNICODE","-D_UNICODE","-DWIN32","-DMINGW_HAS_SECURE_API","-DGIFIMAGE_NO_LIB","-DQT_OPENGLWIDGETS_LIB","-DQT_OPENGL_LIB","-DQT_PRINTSUPPORT_LIB","-DQT_WIDGETS_LIB","-DQT_GUI_LIB","-DQT_CORE_LIB","-DQT_NEEDS_QMAIN","-DQ_CREATOR_RUN","-DQT_ANNOTATE_FUNCTION(x)=__attribute__((annotate(#x)))","-IC:\\Qt\\Tools\\QtCreator\\share\\qtcreator\\cplusplus\\wrappedMingwHeaders","-IC:\\Qt\\Tools\\QtCreator\\share\\qtcreator\\cplusplus\\wrappedQtHeaders","-IC:\\Qt\\Tools\\QtCreator\\share\\qtcreator\\cplusplus\\wrappedQtHeaders\\QtCore","-IC:\\Users\\Dima\\source\\repos\\CPP4_3DViewer_v2.0-2\\src\\3DView","-IC:\\Users\\Dima\\source\\repos\\CPP4_3DViewer_v2.0-2\\src\\3DView\\QtGifImage-master\\src\\gifimage","-IC:\\Users\\Dima\\source\\repos\\CPP4_3DViewer_v2.0-2\\src\\3DView\\QtGifImage-master\\src\\3rdParty\\giflib","-IC:\\Qt\\6.6.3\\mingw_64\\include","-IC:\\Qt\\6.6.3\\mingw_64\\include\\QtOpenGLWidgets","-IC:\\Qt\\6.6.3\\mingw_64\\include\\QtOpenGL","-IC:\\Qt\\6.6.3\\mingw_64\\include\\QtPrintSupport","-IC:\\Qt\\6.6.3\\mingw_64\\include\\QtWidgets","-IC:\\Qt\\6.6.3\\mingw_64\\include\\QtGui","-IC:\\Qt\\6.6.3\\mingw_64\\include\\QtCore","-IC:\\Users\\Dima\\source\\repos\\CPP4_3DViewer_v2.0-2\\src\\3DView\\build\\Desktop_Qt_6_6_3_MinGW_64_bit-Debug\\debug","-IC:\\Users\\Dima\\source\\repos\\CPP4_3DViewer_v2.0-2\\src\\3DView\\build\\Desktop_Qt_6_6_3_MinGW_64_bit-Debug","-IC:\\Qt\\6.6.3\\mingw_64\\mkspecs\\win32-g++","-isystem","C:\\Qt\\Tools\\QtCreator\\bin\\clang\\lib\\clang\\17\\include","-isystem","C:\\Qt\\Tools\\mingw1120_64\\x86_64-w64-mingw32\\include","-fmessage-length=0","-fdiagnostics-show-note-include-stack","-fretain-comments-from-system-headers","-fmacro-backtrace-limit=0","-ferror-limit=1000","-x","c-header","C:\\Users\\Dima\\source\\repos\\CPP4_3DViewer_v2.0-2\\src\\3DView\\model\\affine.h"],"directory":"C:/Users/Dima/source/repos/CPP4_3DViewer_v2.0-2/src/3DView/build/Desktop_Qt_6_6_3_MinGW_64_bit-Debug/.qtc_clangd","file":"C:/Users/Dima/source/repos/CPP4_3DViewer_v2.0-2/src/3DView/model/affine.h"},{"arguments":["clang","-Wno-documentation-unknown-command","-Wno-unknown-warning-option","-Wno-unknown-pragmas","-nostdinc","-nostdinc++","-g","-Wall","-Wextra","-Wextra","-fsyntax-only","-m64","--target=x86_64-w64-mingw32","-std=gnu17","-DUNICODE","-D_UNICODE","-DWIN32","-DMINGW_HAS_SECURE_API","-DGIFIMAGE_NO_LIB","-DQT_OPENGLWIDGETS_LIB","-DQT_OPENGL_LIB","-DQT_PRINTSUPPORT_LIB","-DQT_WIDGETS_LIB","-DQT_GUI_LIB","-DQT_CORE_LIB","-DQT_NEEDS_QMAIN","-DQ_CREATOR_RUN","-DQT_ANNOTATE_FUNCTION(x)=__attribute__((annotate(#x)))","-IC:\\Qt\\Tools\\QtCreator\\share\\qtcreator\\cplusplus\\wrappedMingwHeaders","-IC:\\Qt\\Tools\\QtCreator\\share\\qtcreator\\cplusplus\\wrappedQtHeaders","-IC:\\Qt\\Tools\\QtCreator\\share\\qtcreator\\cplusplus\\wrappedQtHeaders\\QtCore","-IC:\\Users\\Dima\\source\\repos\\CPP4_3DViewer_v2.0-2\\src\\3DView","-IC:\\Users\\Dima\\source\\repos\\CPP4_3DViewer_v2.0-2\\src\\3DView\\QtGifImage-master\\src\\gifimage","-IC:\\Users\\Dima\\source\\repos\\CPP4_3DViewer_v2.0-2\\src\\3DView\\QtGifImage-master\\src\\3rdParty\\giflib","-IC:\\Qt\\6.6.3\\mingw_64\\include","-IC:\\Qt\\6.6.3\\mingw_64\\include\\QtOpenGLWidgets","-IC:\\Qt\\6.6.3\\mingw_64\\include\\QtOpenGL","-IC:\\Qt\\6.6.3\\mingw_64\\include\\QtPrintSupport","-IC:\\Qt\\6.6.3\\mingw_64\\include\\QtWidgets","-IC:\\Qt\\6.6.3\\mingw_64\\include\\QtGui","-IC:\\Qt\\6.6.3\\mingw_64\\include\\QtCore","-IC:\\Users\\Dima\\source\\repos\\CPP4_3DViewer_v2.0-2\\src\\3DView\\build\\Desktop_Qt_6_6_3_MinGW_64_bit-Debug\\debug","-IC:\\Users\\Dima\\source\\repos\\CPP4_3DViewer_v2.0-2\\src\\3DView\\build\\Desktop_Qt_6_6_3_MinGW_64_bit-Debug","-IC:\\Qt\\6.6.3\\mingw_64\\mkspecs\\win32-g++","-isystem","C:\\Qt\\Tools\\QtCreator\\bin\\clang\\lib\\clang\\17\\include","-isystem","C:\\Qt\\Tools\\mingw1120_64\\x86_64-w64-mingw32\\include","-fmessage-length=0","-fdiagnostics-show-note-include-stack","-fretain-comments-from-system-headers","-fmacro-backtrace-limit=0","-ferror-limit=1000","-x","c-header","C:\\Users\\Dima\\source\\repos\\CPP4_3DViewer_v2.0-2\\src\\3DView\\model\\facade.h"],"directory":"C:/Users/Dima/source/repos/CPP4_3DViewer_v2.0-2/src/3DView/build/Desktop_Qt_6_6_3_MinGW_64_bit-Debug/.qtc_clangd","file":"C:/Users/Dima/source/repos/CPP4_3DViewer_v2.0-2/src/3DView/model/facade.h"},{"arguments":["clang","-Wno-documentation-unknown-command","-Wno-unknown-warning-option","-Wno-unknown-pragmas","-nostdinc","-nostdinc++","-g","-Wall","-Wextra","-Wextra","-fsyntax-only","-m64","--target=x86_64-w64-mingw32","-std=gnu17","-DUNICODE","-D_UNICODE","-DWIN32","-DMINGW_HAS_SECURE_API","-DGIFIMAGE_NO_LIB","-DQT_OPENGLWIDGETS_LIB","-DQT_OPENGL_LIB","-DQT_PRINTSUPPORT_LIB","-DQT_WIDGETS_LIB","-DQT_GUI_LIB","-DQT_CORE_LIB","-DQT_NEEDS_QMAIN","-DQ_CREATOR_RUN","-DQT_ANNOTATE_FUNCTION(x)=__attribute__((annotate(#x)))","-IC:\\Qt\\Tools\\QtCreator\\share\\qtcreator\\cplusplus\\wrappedMingwHeaders","-IC:\\Qt\\Tools\\QtCreator\\share\\qtcreator\\cplusplus\\wrappedQtHeaders","-IC:\\Qt\\Tools\\QtCreator\\share\\qtcreator\\cplusplus\\wrappedQtHeaders\\QtCore","-IC:\\Users\\Dima\\source\\repos\\CPP4_3DViewer_v2.0-2\\src\\3DView","-IC:\\Users\\Dima\\source\\repos\\CPP4_3DViewer_v2.0-2\\src\\3DView\\QtGifImage-master\\src\\gifimage","-IC:\\Users\\Dima\\source\\repos\\CPP4_3DViewer_v2.0-2\\src\\3DView\\QtGifImage-master\\src\\3rdParty\\giflib","-IC:\\Qt\\6.6.3\\mingw_64\\include","-IC:\\Qt\\6.6.3\\mingw_64\\include\\QtOpenGLWidgets","-IC:\\Qt\\6.6.3\\mingw_64\\include\\QtOpenGL","-IC:\\Qt\\6.6.3\\mingw_64\\include\\QtPrintSupport","-IC:\\Qt\\6.6.3\\mingw_64\\include\\QtWidgets","-IC:\\Qt\\6.6.3\\mingw_64\\include\\QtGui","-IC:\\Qt\\6.6.3\\mingw_64\\include\\QtCore","-IC:\\Users\\Dima\\source\\repos\\CPP4_3DViewer_v2.0-2\\src\\3DView\\build\\Desktop_Qt_6_6_3_MinGW_64_bit-Debug\\debug","-IC:\\Users\\Dima\\source\\repos\\CPP4_3DViewer_v2.0-2\\src\\3DView\\build\\Desktop_Qt_6_6_3_MinGW_64_bit-Debug","-IC:\\Qt\\6.6.3\\mingw_64\\mkspecs\\win32-g++","-isystem","C:\\Qt\\Tools\\QtCreator\\bin\\clang\\lib\\clang\\17\\include","-isystem","C:\\Qt\\Tools\\mingw1120_64\\x86_64-w64-mingw32\\include","-fmessage-length=0","-fdiagnostics-show-note-include-stack","-fretain-comments-from-system-headers","-fmacro-backtrace-limit=0","-ferror-limit=1000","-x","c-header","C:\\Users\\Dima\\source\\repos\\CPP4_3DViewer_v2.0-2\\src\\3DView\\model\\parser.h"],"directory":"C:/Users/Dima/source/repos/CPP4_3DViewer_v2.0-2/src/3DView/build/Desktop_Qt_6_6_3_MinGW_64_bit-Debug/.qtc_clangd","file":"C:/Users/Dima/source/repos/CPP4_3DViewer_v2.0-2/src/3DView/model/parser.h"},{"arguments":["clang","-Wno-documentation-unknown-command","-Wno-unknown-warning-option","-Wno-unknown-pragmas","-nostdinc","-nostdinc++","-g","-Wall","-Wextra","-Wextra","-fsyntax-only","-m64","--target=x86_64-w64-mingw32","-std=gnu17","-DUNICODE","-D_UNICODE","-DWIN32","-DMINGW_HAS_SECURE_API","-DGIFIMAGE_NO_LIB","-DQT_OPENGLWIDGETS_LIB","-DQT_OPENGL_LIB","-DQT_PRINTSUPPORT_LIB","-DQT_WIDGETS_LIB","-DQT_GUI_LIB","-DQT_CORE_LIB","-DQT_NEEDS_QMAIN","-DQ_CREATOR_RUN","-DQT_ANNOTATE_FUNCTION(x)=__attribute__((annotate(#x)))","-IC:\\Qt\\Tools\\QtCreator\\share\\qtcreator\\cplusplus\\wrappedMingwHeaders","-IC:\\Qt\\Tools\\QtCreator\\share\\qtcreator\\cplusplus\\wrappedQtHeaders","-IC:\\Qt\\Tools\\QtCreator\\share\\qtcreator\\cplusplus\\wrappedQtHeaders\\QtCore","-IC:\\Users\\Dima\\source\\repos\\CPP4_3DViewer_v2.0-2\\src\\3DView","-IC:\\Users\\Dima\\source\\repos\\CPP4_3DViewer_v2.0-2\\src\\3DView\\QtGifImage-master\\src\\gifimage","-IC:\\Users\\Dima\\source\\repos\\CPP4_3DViewer_v2.0-2\\src\\3DView\\QtGifImage-master\\src\\3rdParty\\giflib","-IC:\\Qt\\6.6.3\\mingw_64\\include","-IC:\\Qt\\6.6.3\\mingw_64\\include\\QtOpenGLWidgets","-IC:\\Qt\\6.6.3\\mingw_64\\include\\QtOpenGL","-IC:\\Qt\\6.6.3\\mingw_64\\include\\QtPrintSupport","-IC:\\Qt\\6.6.3\\mingw_64\\include\\QtWidgets","-IC:\\Qt\\6.6.3\\mingw_64\\include\\QtGui","-IC:\\Qt\\6.6.3\\mingw_64\\include\\QtCore","-IC:\\Users\\Dima\\source\\repos\\CPP4_3DViewer_v2.0-2\\src\\3DView\\build\\Desktop_Qt_6_6_3_MinGW_64_bit-Debug\\debug","-IC:\\Users\\Dima\\source\\repos\\CPP4_3DViewer_v2.0-2\\src\\3DView\\build\\Desktop_Qt_6_6_3_MinGW_64_bit-Debug","-IC:\\Qt\\6.6.3\\mingw_64\\mkspecs\\win32-g++","-isystem","C:\\Qt\\Tools\\QtCreator\\bin\\clang\\lib\\clang\\17\\include","-isystem","C:\\Qt\\Tools\\mingw1120_64\\x86_64-w64-mingw32\\include","-fmessage-length=0","-fdiagnostics-show-note-include-stack","-fretain-comments-from-system-headers","-fmacro-backtrace-limit=0","-ferror-limit=1000","-x","c-header","C:\\Users\\Dima\\source\\repos\\CPP4_3DViewer_v2.0-2\\src\\3DView\\view\\glview.h"],"directory":"C:/Users/Dima/source/repos/CPP4_3DViewer_v2.0-2/src/3DView/build/Desktop_Qt_6_6_3_MinGW_64_bit-Debug/.qtc_clangd","file":"C:/Users/Dima/source/repos/CPP4_3DViewer_v2.0-2/src/3DView/view/glview.h"},{"arguments":["clang","-Wno-documentation-unknown-command","-Wno-unknown-warning-option","-Wno-unknown-pragmas","-nostdinc","-nostdinc++","-g","-Wall","-Wextra","-Wextra","-fsyntax-only","-m64","--target=x86_64-w64-mingw32","-std=gnu17","-DUNICODE","-D_UNICODE","-DWIN32","-DMINGW_HAS_SECURE_API","-DGIFIMAGE_NO_LIB","-DQT_OPENGLWIDGETS_LIB","-DQT_OPENGL_LIB","-DQT_PRINTSUPPORT_LIB","-DQT_WIDGETS_LIB","-DQT_GUI_LIB","-DQT_CORE_LIB","-DQT_NEEDS_QMAIN","-DQ_CREATOR_RUN","-DQT_ANNOTATE_FUNCTION(x)=__attribute__((annotate(#x)))","-IC:\\Qt\\Tools\\QtCreator\\share\\qtcreator\\cplusplus\\wrappedMingwHeaders","-IC:\\Qt\\Tools\\QtCreator\\share\\qtcreator\\cplusplus\\wrappedQtHeaders","-IC:\\Qt\\Tools\\QtCreator\\share\\qtcreator\\cplusplus\\wrappedQtHeaders\\QtCore","-IC:\\Users\\Dima\\source\\repos\\CPP4_3DViewer_v2.0-2\\src\\3DView","-IC:\\Users\\Dima\\source\\repos\\CPP4_3DViewer_v2.0-2\\src\\3DView\\QtGifImage-master\\src\\gifimage","-IC:\\Users\\Dima\\source\\repos\\CPP4_3DViewer_v2.0-2\\src\\3DView\\QtGifImage-master\\src\\3rdParty\\giflib","-IC:\\Qt\\6.6.3\\mingw_64\\include","-IC:\\Qt\\6.6.3\\mingw_64\\include\\QtOpenGLWidgets","-IC:\\Qt\\6.6.3\\mingw_64\\include\\QtOpenGL","-IC:\\Qt\\6.6.3\\mingw_64\\include\\QtPrintSupport","-IC:\\Qt\\6.6.3\\mingw_64\\include\\QtWidgets","-IC:\\Qt\\6.6.3\\mingw_64\\include\\QtGui","-IC:\\Qt\\6.6.3\\mingw_64\\include\\QtCore","-IC:\\Users\\Dima\\source\\repos\\CPP4_3DViewer_v2.0-2\\src\\3DView\\build\\Desktop_Qt_6_6_3_MinGW_64_bit-Debug\\debug","-IC:\\Users\\Dima\\source\\repos\\CPP4_3DViewer_v2.0-2\\src\\3DView\\build\\Desktop_Qt_6_6_3_MinGW_64_bit-Debug","-IC:\\Qt\\6.6.3\\mingw_64\\mkspecs\\win32-g++","-isystem","C:\\Qt\\Tools\\QtCreator\\bin\\clang\\lib\\clang\\17\\include","-isystem","C:\\Qt\\Tools\\mingw1120_64\\x86_64-w64-mingw32\\include","-fmessage-length=0","-fdiagnostics-show-note-include-stack","-fretain-comments-from-system-headers","-fmacro-backtrace-limit=0","-ferror-limit=1000","-x","c-header","C:\\Users\\Dima\\source\\repos\\CPP4_3DViewer_v2.0-2\\src\\3DView\\mainwindow.h"],"directory":"C:/Users/Dima/source/repos/CPP4_3DViewer_v2.0-2/src/3DView/build/Desktop_Qt_6_6_3_MinGW_64_bit-Debug/.qtc_clangd","file":"C:/Users/Dima/source/repos/CPP4_3DViewer_v2.0-2/src/3DView/mainwindow.h"},{"arguments":["clang","-Wno-documentation-unknown-command","-Wno-unknown-warning-option","-Wno-unknown-pragmas","-nostdinc","-nostdinc++","-g","-Wall","-Wextra","-Wextra","-fsyntax-only","-m64","--target=x86_64-w64-mingw32","-std=gnu17","-DUNICODE","-D_UNICODE","-DWIN32","-DMINGW_HAS_SECURE_API","-DGIFIMAGE_NO_LIB","-DQT_OPENGLWIDGETS_LIB","-DQT_OPENGL_LIB","-DQT_PRINTSUPPORT_LIB","-DQT_WIDGETS_LIB","-DQT_GUI_LIB","-DQT_CORE_LIB","-DQT_NEEDS_QMAIN","-DQ_CREATOR_RUN","-DQT_ANNOTATE_FUNCTION(x)=__attribute__((annotate(#x)))","-IC:\\Qt\\Tools\\QtCreator\\share\\qtcreator\\cplusplus\\wrappedMingwHeaders","-IC:\\Qt\\Tools\\QtCreator\\share\\qtcreator\\cplusplus\\wrappedQtHeaders","-IC:\\Qt\\Tools\\QtCreator\\share\\qtcreator\\cplusplus\\wrappedQtHeaders\\QtCore","-IC:\\Users\\Dima\\source\\repos\\CPP4_3DViewer_v2.0-2\\src\\3DView","-IC:\\Users\\Dima\\source\\repos\\CPP4_3DViewer_v2.0-2\\src\\3DView\\QtGifImage-master\\src\\gifimage","-IC:\\Users\\Dima\\source\\repos\\CPP4_3DViewer_v2.0-2\\src\\3DView\\QtGifImage-master\\src\\3rdParty\\giflib","-IC:\\Qt\\6.6.3\\mingw_64\\include","-IC:\\Qt\\6.6.3\\mingw_64\\include\\QtOpenGLWidgets","-IC:\\Qt\\6.6.3\\mingw_64\\include\\QtOpenGL","-IC:\\Qt\\6.6.3\\mingw_64\\include\\QtPrintSupport","-IC:\\Qt\\6.6.3\\mingw_64\\include\\QtWidgets","-IC:\\Qt\\6.6.3\\mingw_64\\include\\QtGui","-IC:\\Qt\\6.6.3\\mingw_64\\include\\QtCore","-IC:\\Users\\Dima\\source\\repos\\CPP4_3DViewer_v2.0-2\\src\\3DView\\build\\Desktop_Qt_6_6_3_MinGW_64_bit-Debug\\debug","-IC:\\Users\\Dima\\source\\repos\\CPP4_3DViewer_v2.0-2\\src\\3DView\\build\\Desktop_Qt_6_6_3_MinGW_64_bit-Debug","-IC:\\Qt\\6.6.3\\mingw_64\\mkspecs\\win32-g++","-isystem","C:\\Qt\\Tools\\QtCreator\\bin\\clang\\lib\\clang\\17\\include","-isystem","C:\\Qt\\Tools\\mingw1120_64\\x86_64-w64-mingw32\\include","-fmessage-length=0","-fdiagnostics-show-note-include-stack","-fretain-comments-from-system-headers","-fmacro-backtrace-limit=0","-ferror-limit=1000","-x","c-header","C:\\Users\\Dima\\source\\repos\\CPP4_3DViewer_v2.0-2\\src\\3DView\\view\\record_media.h"],"directory":"C:/Users/Dima/source/repos/CPP4_3DViewer_v2.0-2/src/3DView/build/Desktop_Qt_6_6_3_MinGW_64_bit-Debug/.qtc_clangd","file":"C:/Users/Dima/source/repos/CPP4_3DViewer_v2.0-2/src/3DView/view/record_media.h"},{"arguments":["clang","-Wno-documentation-unknown-command","-Wno-unknown-warning-option","-Wno-unknown-pragmas","-nostdinc","-nostdinc++","-g","-Wall","-Wextra","-Wextra","-fsyntax-only","-m64","--target=x86_64-w64-mingw32","-std=gnu17","-DUNICODE","-D_UNICODE","-DWIN32","-DMINGW_HAS_SECURE_API","-DGIFIMAGE_NO_LIB","-DQT_OPENGLWIDGETS_LIB","-DQT_OPENGL_LIB","-DQT_PRINTSUPPORT_LIB","-DQT_WIDGETS_LIB","-DQT_GUI_LIB","-DQT_CORE_LIB","-DQT_NEEDS_QMAIN","-DQ_CREATOR_RUN","-DQT_ANNOTATE_FUNCTION(x)=__attribute__((annotate(#x)))","-IC:\\Qt\\Tools\\QtCreator\\share\\qtcreator\\cplusplus\\wrappedMingwHeaders","-IC:\\Qt\\Tools\\QtCreator\\share\\qtcreator\\cplusplus\\wrappedQtHeaders","-IC:\\Qt\\Tools\\QtCreator\\share\\qtcreator\\cplusplus\\wrappedQtHeaders\\QtCore","-IC:\\Users\\Dima\\source\\repos\\CPP4_3DViewer_v2.0-2\\src\\3DView","-IC:\\Users\\Dima\\source\\repos\\CPP4_3DViewer_v2.0-2\\src\\3DView\\QtGifImage-master\\src\\gifimage","-IC:\\Users\\Dima\\source\\repos\\CPP4_3DViewer_v2.0-2\\src\\3DView\\QtGifImage-master\\src\\3rdParty\\giflib","-IC:\\Qt\\6.6.3\\mingw_64\\include","-IC:\\Qt\\6.6.3\\mingw_64\\include\\QtOpenGLWidgets","-IC:\\Qt\\6.6.3\\mingw_64\\include\\QtOpenGL","-IC:\\Qt\\6.6.3\\mingw_64\\include\\QtPrintSupport","-IC:\\Qt\\6.6.3\\mingw_64\\include\\QtWidgets","-IC:\\Qt\\6.6.3\\mingw_64\\include\\QtGui","-IC:\\Qt\\6.6.3\\mingw_64\\include\\QtCore","-IC:\\Users\\Dima\\source\\repos\\CPP4_3DViewer_v2.0-2\\src\\3DView\\build\\Desktop_Qt_6_6_3_MinGW_64_bit-Debug\\debug","-IC:\\Users\\Dima\\source\\repos\\CPP4_3DViewer_v2.0-2\\src\\3DView\\build\\Desktop_Qt_6_6_3_MinGW_64_bit-Debug","-IC:\\Qt\\6.6.3\\mingw_64\\mkspecs\\win32-g++","-isystem","C:\\Qt\\Tools\\QtCreator\\bin\\clang\\lib\\clang\\17\\include","-isystem","C:\\Qt\\Tools\\mingw1120_64\\x86_64-w64-mingw32\\include","-fmessage-length=0","-fdiagnostics-show-note-include-stack","-fretain-comments-from-system-headers","-fmacro-backtrace-limit=0","-ferror-limit=1000","-x","c-header","C:\\Users\\Dima\\source\\repos\\CPP4_3DViewer_v2.0-2\\src\\3DView\\build\\Desktop_Qt_6_6_3_MinGW_64_bit-Debug\\ui_mainwindow.h"],"directory":"C:/Users/Dima/source/repos/CPP4_3DViewer_v2.0-2/src/3DView/build/Desktop_Qt_6_6_3_MinGW_64_bit-Debug/.qtc_clangd","file":"C:/Users/Dima/source/repos/CPP4_3DViewer_v2.0-2/src/3DView/build/Desktop_Qt_6_6_3_MinGW_64_bit-Debug/ui_mainwindow.h"}]